[
    {
        "title": "피파 인생 2년 최대 위기에 놓인 임유진.. 이대로 뿌드컵 광탈?",
        "views": "조회수 5.3만회",
        "upload_date": "2주 전",
        "channel_name": "임유진"
    },
    {
        "title": "뿌꾸님의 800조 포르투갈로 뿌드컵 우승하겠습니다",
        "views": "조회수 6.9만회",
        "upload_date": "2주 전",
        "channel_name": "임유진"
    },
    {
        "title": "[JOY BOX] 형수님 오늘 6언더 잡겠네~ 윤태영 아내 임유진 마라맛 입담에 탈주하는 윤태영과 팝콘각 골프왕ㅋㅋㅋ #골프왕 #TV조선조이 (TV CHOSUN 220611 방송)",
        "views": "조회수 75만회",
        "upload_date": "2년 전",
        "channel_name": "TVCHOSUN JOY"
    },
    {
        "title": "피창인생 2년 만에 키보드 챔스 찍었습니다..",
        "views": "조회수 24만회",
        "upload_date": "4개월 전",
        "channel_name": "임유진"
    },
    {
        "title": "윤태영, 아내 임유진 “뇌 수술에 하늘이 무너져 내려.. 아내 만나 사람 됐는데” 울컥",
        "views": "조회수 8.5만회",
        "upload_date": "5개월 전",
        "channel_name": "스브스 트렌즈"
    },
    {
        "title": "600조 맨유 달성하신 상호님 거울 치료로 혼내드리기ㅋㅋ",
        "views": "조회수 17만회",
        "upload_date": "3개월 전",
        "channel_name": "임유진"
    },
    {
        "title": "1000억 올금카팀 박찬화 VS 1000조 뿌꾸 임유진",
        "views": "조회수 13만회",
        "upload_date": "3개월 전",
        "channel_name": "두치와뿌꾸"
    },
    {
        "title": "본캐 바르샤 결국 \" 그 선수 \" 영입 했습니다.. 미친 드리블과 체감ㄷㄷ",
        "views": "조회수 11만회",
        "upload_date": "3주 전",
        "channel_name": "임유진"
    },
    {
        "title": "이 팀 무과금으로 하시면.. | 무과금 부캐 키우기",
        "views": "조회수 39만회",
        "upload_date": "1년 전",
        "channel_name": "임유진"
    },
    {
        "title": "Siuuuuuuuuuu 호여동생 왔습니다",
        "views": "조회수 32만회",
        "upload_date": "1년 전",
        "channel_name": "임유진"
    },
    {
        "title": "FC온라인이 뭐예요?",
        "views": "조회수 29만회",
        "upload_date": "11개월 전",
        "channel_name": "임유진"
    },
    {
        "title": "뭔가 잘못된 거 같다..",
        "views": "조회수 20만회",
        "upload_date": "1년 전",
        "channel_name": "임유진"
    },
    {
        "title": "체감 GOAT '필 포든 47 금카' 영입하고 준홍시치 쏴버렸습니다",
        "views": "조회수 26만회",
        "upload_date": "3개월 전",
        "channel_name": "임유진"
    },
    {
        "title": "피파 복귀한 감스트님에게 골 넣고 관제탑 세레머니 하기 ㅋㅋㅋㅋ",
        "views": "조회수 22만회",
        "upload_date": "2개월 전",
        "channel_name": "임유진"
    },
    {
        "title": "여러분은 이제 이 노래에 빠져듭니다.. 루루루루루 루니~",
        "views": "조회수 14만회",
        "upload_date": "4개월 전",
        "channel_name": "임유진"
    },
    {
        "title": "준홍이 180조 CC 호날두 금카 샀네? 1000억 HOT두로 방어 간다!!!!!",
        "views": "조회수 31만회",
        "upload_date": "2개월 전",
        "channel_name": "임유진"
    },
    {
        "title": "더 이상 떨어질 곳이 없다.. 피파판 최약체가 되기 직전인 그녀의 운명은?",
        "views": "조회수 10만회",
        "upload_date": "1개월 전",
        "channel_name": "임유진"
    },
    {
        "title": "미친 황금맛 스탯의 미드필더 영입했습니다ㅋㅋㅋ 오버롤 143 실화냐",
        "views": "조회수 14만회",
        "upload_date": "3개월 전",
        "channel_name": "임유진"
    },
    {
        "title": "정준홍의 호날두 vs 임유진의 메시",
        "views": "조회수 7.3만회",
        "upload_date": "3주 전",
        "channel_name": "임유진"
    },
    {
        "title": "강화는 못해도 빠칭코는 수상하리 만큼 잘하는 여자",
        "views": "조회수 10만회",
        "upload_date": "3개월 전",
        "channel_name": "임유진"
    },
    {
        "title": "본캐 바르셀로나 팀갈.. 근데 ”이 선수“를 쓴다구요?",
        "views": "조회수 12만회",
        "upload_date": "4주 전",
        "channel_name": "임유진"
    },
    {
        "title": "본캐 잉글랜드 신상 대장 시즌 조콜 금카 영입 했습니다 ㄷㄷ.. 레전드네?",
        "views": "조회수 15만회",
        "upload_date": "4개월 전",
        "channel_name": "임유진"
    },
    {
        "title": "임유진 언젠간 진짜 주먹으로 때린다",
        "views": "조회수 23만회",
        "upload_date": "5개월 전",
        "channel_name": "유봉훈"
    },
    {
        "title": "돌아온 잉유진.. 본캐 150조 중거리 맛집 뻥글랜드 맞췄습니다",
        "views": "조회수 21만회",
        "upload_date": "5개월 전",
        "channel_name": "임유진"
    },
    {
        "title": "피파 여자 1등을 하시겠다구요? 아니 여러분 어디 가세요?",
        "views": "조회수 12만회",
        "upload_date": "3개월 전",
        "channel_name": "임유진"
    },
    {
        "title": "다른 지역 pc방 가서 모르는 사람과 1:1 피파 이기고 오기 벌칙",
        "views": "조회수 14만회",
        "upload_date": "4개월 전",
        "channel_name": "임유진"
    },
    {
        "title": "피파 여신 임유진님이 영미터 방송에?! 본계정 김민재 영입까지! FC모바일",
        "views": "조회수 5.2만회",
        "upload_date": "7개월 전",
        "channel_name": "영미터"
    },
    {
        "title": "히트(임유진)  - My Way",
        "views": "조회수 4.7만회",
        "upload_date": "7년 전",
        "channel_name": "가요올드스쿨"
    },
    {
        "title": "공감력 부족 임유진 제대로 감수성 키워주기 대작전",
        "views": "조회수 16만회",
        "upload_date": "2개월 전",
        "channel_name": "유봉훈"
    },
    {
        "title": "본캐 24토츠 벨링엄 강화했습니다 그리고 신규 드리블 미쳤는데?",
        "views": "조회수 16만회",
        "upload_date": "2개월 전",
        "channel_name": "임유진"
    },
    {
        "title": "본캐 250조 잉글랜드 다 팔았습니다.. 저 이제 떠날게요",
        "views": "조회수 16만회",
        "upload_date": "1개월 전",
        "channel_name": "임유진"
    },
    {
        "title": "저 한국으로 팀갈이 하고 싶어졌습니다",
        "views": "조회수 21만회",
        "upload_date": "6개월 전",
        "channel_name": "임유진"
    },
    {
        "title": "문워크 처음 당해보는 임유진.. 저랑 다시는 피파 안 한다고 하네요 ㅋㅋㅋㅋ",
        "views": "조회수 84만회",
        "upload_date": "1년 전",
        "channel_name": "이상호"
    },
    {
        "title": "본캐 최강 2조 레알 마드리드로 팀갈 완료",
        "views": "조회수 44만회",
        "upload_date": "1년 전",
        "channel_name": "임유진"
    },
    {
        "title": "일타봉쌤 돌팔이죠? 케인이 안 좋다구요?ㅋㅋ 이 영상을 보셔야 합니다",
        "views": "조회수 15만회",
        "upload_date": "4개월 전",
        "channel_name": "임유진"
    },
    {
        "title": "cu 금카팩 뽑기 장인 #shorts",
        "views": "조회수 4.6만회",
        "upload_date": "8일 전",
        "channel_name": "임유진"
    },
    {
        "title": "감스트 박주영 금카 영입! 진짜 개사기네요.. + 임유진님과 대결 피파4",
        "views": "조회수 247만회",
        "upload_date": "1년 전",
        "channel_name": "감스트GAMST"
    },
    {
        "title": "꾸티뉴의 영원한 샌드백 '임유진'",
        "views": "조회수 22만회",
        "upload_date": "1년 전",
        "channel_name": "꾸티뉴"
    },
    {
        "title": "본캐 잉글랜드 레전드 황금맛 스탯 윙어 영입 ㄷㄷ.. 170조 구단 완성!",
        "views": "조회수 14만회",
        "upload_date": "4개월 전",
        "channel_name": "임유진"
    },
    {
        "title": "임유진 볼살 논란",
        "views": "조회수 213만회",
        "upload_date": "1년 전",
        "channel_name": "임유진"
    },
    {
        "title": "회사 그만두고 피파 프로게이머가 되신 분과 1:1 떠봤는데.. 어라?",
        "views": "조회수 8.1만회",
        "upload_date": "1개월 전",
        "channel_name": "임유진"
    },
    {
        "title": "음바페, 메시와의 만남.. | 무과금 부캐 키우기",
        "views": "조회수 35만회",
        "upload_date": "1년 전",
        "channel_name": "임유진"
    },
    {
        "title": "‘불꽃 용기’ 윤태영, 임유진과 결혼 위한 드라마 같은 선전포고♥ #동상이몽2 #YouareMyDestiny #SBSenter",
        "views": "조회수 28만회",
        "upload_date": "1년 전",
        "channel_name": "SBS Entertainment"
    },
    {
        "title": "결국 해버렸습니다 | 무과금 부캐 키우기",
        "views": "조회수 36만회",
        "upload_date": "1년 전",
        "channel_name": "임유진"
    },
    {
        "title": "이상호의 리즈시절",
        "views": "조회수 104만회",
        "upload_date": "1년 전",
        "channel_name": "텐끼피파"
    },
    {
        "title": "센터백에 처음 5조 써봤습니다! 52조 유진투스 드디어 완성???",
        "views": "조회수 19만회",
        "upload_date": "8개월 전",
        "channel_name": "임유진"
    },
    {
        "title": "신규 시즌 나왔다길래 본캐 200만원치 패키지 사봤는데..?!",
        "views": "조회수 17만회",
        "upload_date": "1년 전",
        "channel_name": "임유진"
    },
    {
        "title": "히트 - My way (60fps) 2000.0102",
        "views": "조회수 7.6천회",
        "upload_date": "3년 전",
        "channel_name": "MUSIC나루"
    },
    {
        "title": "\"지금 당장 서울에서 부산 가서 입수하고 국밥 먹기\"",
        "views": "조회수 28만회",
        "upload_date": "7개월 전",
        "channel_name": "임유진"
    },
    {
        "title": "채팅을 끄게 된 이유.. 팀빨이든 뭐든 너보단 잘 해",
        "views": "조회수 18만회",
        "upload_date": "10개월 전",
        "channel_name": "임유진"
    },
    {
        "title": "가만히 있는데 시비 거는 잼민이 유저.. 이런 애들 정지 좀요 제발",
        "views": "조회수 10만회",
        "upload_date": "8개월 전",
        "channel_name": "임유진"
    },
    {
        "title": "하루에 호돈을 2번 뽑는 여자 #shorts",
        "views": "조회수 48만회",
        "upload_date": "3개월 전",
        "channel_name": "임유진"
    },
    {
        "title": "상위 1% 찐재벌 윤태영X임유진 결혼도 평범하지 않다💗 차원이 다른 블랙 카드 FLEX💸  #동상이몽2 #YouareMyDestiny #SBSCatch",
        "views": "조회수 119만회",
        "upload_date": "5개월 전",
        "channel_name": "SBS Catch"
    },
    {
        "title": "감스트님에게 복수했습니다",
        "views": "조회수 26만회",
        "upload_date": "1년 전",
        "channel_name": "임유진"
    },
    {
        "title": "다리가 너무 가려워서 그만..",
        "views": "조회수 61만회",
        "upload_date": "7개월 전",
        "channel_name": "이상호"
    },
    {
        "title": "확실히 잉글랜드가 맛있긴 하네..",
        "views": "조회수 6.9만회",
        "upload_date": "3개월 전",
        "channel_name": "임유진"
    },
    {
        "title": "돌고 돌아 레알 마드리드로 정착했습니다.. 2달 동안 1600만원 현질 실화야?!",
        "views": "조회수 27만회",
        "upload_date": "1년 전",
        "channel_name": "임유진"
    },
    {
        "title": "재벌 아들 윤태영이 임유진과 결혼한 진짜 이유",
        "views": "조회수 11만회",
        "upload_date": "5개월 전",
        "channel_name": "고추밭"
    },
    {
        "title": "돌아온 암살.. 아니 요리 교실! 임유진의 김치볶음밥과 된찌 (feat. 믹슈, 강준호)",
        "views": "조회수 7.1만회",
        "upload_date": "2개월 전",
        "channel_name": "임유진"
    },
    {
        "title": "임유진 만나고 싶다던 감스트님.. 드디어 만났습니다",
        "views": "조회수 16만회",
        "upload_date": "1년 전",
        "channel_name": "임유진"
    },
    {
        "title": "오버롤 155인 24토티 벨링엄 10카 써봤습니다ㅋㅋㅋ [FC 프로 마스터즈]",
        "views": "조회수 13만회",
        "upload_date": "4개월 전",
        "channel_name": "임유진"
    },
    {
        "title": "브..이??🤦 요즘 애들은 브이🤞🏻를 이렇게 한다며? TV CHOSUN 220611 방송 | [골프왕3] 10회  | TV조선",
        "views": "조회수 20만회",
        "upload_date": "2년 전",
        "channel_name": "TVCHOSUN - TV조선"
    },
    {
        "title": "상호님이 지원해주신 본캐 400만원 카드깡 80배가 떴습니다!!!!!",
        "views": "조회수 35만회",
        "upload_date": "1년 전",
        "channel_name": "임유진"
    },
    {
        "title": "[JOY BOX] 필드에서 부부 싸움 하다?! 맨발 윤태영 VS 양말 임유진의 대결 결과는? #골프왕 #TV조선조이 (TV CHOSUN 220611 방송)",
        "views": "조회수 32만회",
        "upload_date": "2년 전",
        "channel_name": "TVCHOSUN JOY"
    },
    {
        "title": "뿌꾸님의 29조 공격수.. 13억 벤제마로 혼내드렸습니다ㅋㅋㅋ",
        "views": "조회수 29만회",
        "upload_date": "1년 전",
        "channel_name": "임유진"
    },
    {
        "title": "임유진 코카인 보고 표정 관리 실패한 케이",
        "views": "조회수 107만회",
        "upload_date": "1년 전",
        "channel_name": "케미 모음집"
    },
    {
        "title": "\"임유진 게임 ㅈㄴ 못하게 생겨서 잘하네?\"",
        "views": "조회수 20만회",
        "upload_date": "1년 전",
        "channel_name": "임유진"
    },
    {
        "title": "올킬하고 임유진 꼬시려는 꾸티뉴ㅋㅋㅋㅋㅋㅋㅋㅋ",
        "views": "조회수 20만회",
        "upload_date": "5개월 전",
        "channel_name": "꾸티뉴"
    },
    {
        "title": "민교님을 화나게 만든 그 ‘콧노래’",
        "views": "조회수 26만회",
        "upload_date": "1년 전",
        "channel_name": "임유진"
    },
    {
        "title": "내 귀에 캔디 feat.임유진",
        "views": "조회수 31만회",
        "upload_date": "6개월 전",
        "channel_name": "마빡"
    },
    {
        "title": "30조 레알 VS 8조 레알.. 팀 바꿨더니 똑같이 혼나는 백크ㅋㅋㅋㅋ",
        "views": "조회수 31만회",
        "upload_date": "1년 전",
        "channel_name": "임유진"
    },
    {
        "title": "어느 아나운서의 변신",
        "views": "조회수 660만회",
        "upload_date": "2년 전",
        "channel_name": "이슈저장소_DISV"
    },
    {
        "title": "95억 올금카팀 VS 1000조 뿌꾸 챔스 임유진",
        "views": "조회수 20만회",
        "upload_date": "4개월 전",
        "channel_name": "두치와뿌꾸"
    },
    {
        "title": "사랑의 찬가 Hymne á l’Amour - 임유진 Yoojin Lim",
        "views": "조회수 5.2만회",
        "upload_date": "9년 전",
        "channel_name": "Artists United 아티스트 유나이티드"
    },
    {
        "title": "서버 1위 토트넘 구단 체험ㄷㄷ.. 손흥민 감아차기는 전설이다",
        "views": "조회수 18만회",
        "upload_date": "6개월 전",
        "channel_name": "임유진"
    },
    {
        "title": "Una Furtiva Lagrima 남몰래 흐르는 눈물 - 임유진 Yoojin Lim",
        "views": "조회수 15만회",
        "upload_date": "9년 전",
        "channel_name": "Artists United 아티스트 유나이티드"
    },
    {
        "title": "50억 리버풀 맞췄습니다 | 무과금 부캐 키우기",
        "views": "조회수 38만회",
        "upload_date": "1년 전",
        "channel_name": "임유진"
    },
    {
        "title": "1카팩 레전드",
        "views": "조회수 118만회",
        "upload_date": "1년 전",
        "channel_name": "임유진"
    },
    {
        "title": "임유진 접게 만들어버렸습니다 미안해요 여러분",
        "views": "조회수 36만회",
        "upload_date": "9개월 전",
        "channel_name": "유봉훈"
    },
    {
        "title": "사랑의 찬가 - 임유진 @ 힐링유",
        "views": "조회수 11만회",
        "upload_date": "9년 전",
        "channel_name": "CGN"
    },
    {
        "title": "TA OSRㅡ게스트 임유진 EDC",
        "views": "조회수 1.2만회",
        "upload_date": "1년 전",
        "channel_name": "Together Achieve"
    },
    {
        "title": "임유진의 50배 불꽃쇼",
        "views": "조회수 39만회",
        "upload_date": "1년 전",
        "channel_name": "임유진"
    },
    {
        "title": "찐 민호특공대💖 골프왕을 찾은 이유는 남편 아니고 민호 TV CHOSUN 220611 방송 | [골프왕3] 10회  | TV조선",
        "views": "조회수 13만회",
        "upload_date": "2년 전",
        "channel_name": "TVCHOSUN - TV조선"
    },
    {
        "title": "신길동 매운 짬뽕을 먹고 왔습니다.. 이거 먹는 거 맞나요?",
        "views": "조회수 14만회",
        "upload_date": "8개월 전",
        "channel_name": "임유진"
    },
    {
        "title": "지금 이 선수팩 미쳤습니다..",
        "views": "조회수 21만회",
        "upload_date": "1년 전",
        "channel_name": "임유진"
    },
    {
        "title": "피파 1,2황 다 패고 다닌다는 임유진의 포를란 ㄷㄷ",
        "views": "조회수 17만회",
        "upload_date": "1년 전",
        "channel_name": "울산큰고래 박성주"
    },
    {
        "title": "뿌꾸vs임유진 \"그거 TT호나우두 아니에요?\" 첫판부터 시작된 입딜 ㅋㅋㅋㅋ",
        "views": "조회수 15만회",
        "upload_date": "4개월 전",
        "channel_name": "두치와뿌꾸"
    },
    {
        "title": "23토티 은카를 무려 3장이나 뽑은 여자.. 바로 나 임유진",
        "views": "조회수 25만회",
        "upload_date": "1년 전",
        "channel_name": "임유진"
    },
    {
        "title": "[JOY #Shorts] 아내 임유진을 향한 사랑꾼 윤태영의 영상 편지 #골프왕 #TV조선조이 #TVCHOSUNJOY (TV CHOSUN 220611 방송)",
        "views": "조회수 19만회",
        "upload_date": "2년 전",
        "channel_name": "TVCHOSUN JOY"
    },
    {
        "title": "전개 배워온 상호님.. 다시 중거리 돈슛 원툴로 돌려보내드릴게요ㅋㅋㅋ",
        "views": "조회수 14만회",
        "upload_date": "1년 전",
        "channel_name": "임유진"
    },
    {
        "title": "임유진 그게 무슨 개떡같은 소리야",
        "views": "조회수 6.6만회",
        "upload_date": "2개월 전",
        "channel_name": "두치와뿌꾸"
    },
    {
        "title": "6억 올금카팀 곽준혁 VS 700조 본캐 뿌꾸 임유진 이건 잡는다",
        "views": "조회수 12만회",
        "upload_date": "4개월 전",
        "channel_name": "두치와뿌꾸"
    },
    {
        "title": "본캐에도 드디어 떴습니다.. 정무형 고마워요 (처음으로)",
        "views": "조회수 12만회",
        "upload_date": "6개월 전",
        "channel_name": "임유진"
    },
    {
        "title": "서버 종결 24토츠 손흥민 금카.. 속가, 골결, 슛파워 다 150 넘네 미쳤네;",
        "views": "조회수 12만회",
        "upload_date": "1개월 전",
        "channel_name": "임유진"
    },
    {
        "title": "챔스 찍은 임유진 본캐 CC두 금카로 어깨부시기",
        "views": "조회수 15만회",
        "upload_date": "4개월 전",
        "channel_name": "두치와뿌꾸"
    },
    {
        "title": "임유진ㅣFS 경기번호53-2. 여자 초급 동호인12ㅅ 이하부 2ㅎㄴ 11조ㅣ2024-07-27 교보생명컵 꿈나무대회 1일차ㅣ트리플",
        "views": "조회수 178회",
        "upload_date": "1개월 전",
        "channel_name": "JewelskatersCross"
    },
    {
        "title": "유봉훈이 168cm 키퍼 VS 1200조 뿌꾸 임유진 개웃김ㅋㅋ",
        "views": "조회수 28만회",
        "upload_date": "3개월 전",
        "channel_name": "두치와뿌꾸"
    },
    {
        "title": "본캐 임유진한테 폭풍현질 맡겼더니 대박났다!!!",
        "views": "조회수 26만회",
        "upload_date": "1년 전",
        "channel_name": "두치와뿌꾸"
    },
    {
        "title": "우리 형과 함께 갈 나의 다음 팀은?",
        "views": "조회수 14만회",
        "upload_date": "8개월 전",
        "channel_name": "임유진"
    },
    {
        "title": "여호와는 나의 목자시니 - 임유진 @ 힐링유",
        "views": "조회수 1.2만회",
        "upload_date": "9년 전",
        "channel_name": "CGN"
    },
    {
        "title": "히트(임유진) - My way (MV) (1999)",
        "views": "조회수 5.9만회",
        "upload_date": "8년 전",
        "channel_name": "Old Kpop추억의뮤비"
    },
    {
        "title": "사라진 1조 3천억.. 정무님 강화 확률 해명 부탁드립니다",
        "views": "조회수 14만회",
        "upload_date": "1년 전",
        "channel_name": "임유진"
    },
    {
        "title": "[방송사고] 문신존잘일진 노래 중 마이크 켜진 줄 몰랐던 여자",
        "views": "조회수 671만회",
        "upload_date": "1년 전",
        "channel_name": "커맨더지코"
    },
    {
        "title": "임유진의 제로투 몰래 관음하는 훈발놈 ㅋㅋAV배우인줄",
        "views": "조회수 72만회",
        "upload_date": "1년 전",
        "channel_name": "훈이형 Hun2bro"
    },
    {
        "title": "꾸진스.. 한강에서 데이트 포착",
        "views": "조회수 26만회",
        "upload_date": "1년 전",
        "channel_name": "꾸티뉴"
    },
    {
        "title": "'삼성 부회장 아들' 배우 윤태영, 자신 둘러싼 소문·아내 임유진 언급 '화제' #shorts / 이포커스",
        "views": "조회수 195만회",
        "upload_date": "1년 전",
        "channel_name": "이포커스"
    },
    {
        "title": "120만원으로 4600억 만들기",
        "views": "조회수 25만회",
        "upload_date": "1년 전",
        "channel_name": "임유진"
    },
    {
        "title": "앞으로 제 피파 롤모델은 이상호님입니다",
        "views": "조회수 17만회",
        "upload_date": "1년 전",
        "channel_name": "임유진"
    },
    {
        "title": "[JOY BOX] 민호특공대 임유진 그린에서 장민호와 만나버렸다;;ㄷㄷ 과연 승자는 누구?! #골프왕 #TV조선조이 (TV CHOSUN 220611 방송)",
        "views": "조회수 18만회",
        "upload_date": "2년 전",
        "channel_name": "TVCHOSUN JOY"
    },
    {
        "title": "패키지를 가장 잘 띄우는 BJ는 누굴까..?",
        "views": "조회수 15만회",
        "upload_date": "1년 전",
        "channel_name": "임유진"
    },
    {
        "title": "500억 상속남 윤태영, 父주식 증여세 소송 결국 승소... 방송 종 눈물 펑펑 쏟은 이유 ft. 아내 임유진",
        "views": "조회수 7.4만회",
        "upload_date": "1년 전",
        "channel_name": "연예인국민이슈"
    },
    {
        "title": "22챔 나폴리 코인 미남홀란드에게도 지는 사람이 있다..?",
        "views": "조회수 17만회",
        "upload_date": "1년 전",
        "channel_name": "임유진"
    },
    {
        "title": "임유진이 우리집에와서 술먹방 이걸로했습니다... Feat. 스카우터",
        "views": "조회수 2.1만회",
        "upload_date": "7개월 전",
        "channel_name": "마빡"
    },
    {
        "title": "영정 풀어달라며 집으로 찾아온 여BJ",
        "views": "조회수 25만회",
        "upload_date": "2년 전",
        "channel_name": "튜브김민교"
    },
    {
        "title": "임유진한테 머리스타일 물어봤습니다",
        "views": "조회수 1.9만회",
        "upload_date": "2개월 전",
        "channel_name": "마빡"
    },
    {
        "title": "임유진 샷건 모음",
        "views": "조회수 24만회",
        "upload_date": "1년 전",
        "channel_name": "임유진"
    },
    {
        "title": "서버 최초 420조 24토츠 금카 단일팀! 어떻게 구하셨어요..?",
        "views": "조회수 8.5만회",
        "upload_date": "4주 전",
        "channel_name": "임유진"
    },
    {
        "title": "빅윈님과 진짜 유벤투스 가리기! 지는 사람은 머슴이 되는 겁니다 ㅋㅋㅋ",
        "views": "조회수 8.4만회",
        "upload_date": "7개월 전",
        "channel_name": "임유진"
    },
    {
        "title": "피파로 여자 울리는 이상호..근데 혹시 풀캠 가능한가요??",
        "views": "조회수 31만회",
        "upload_date": "1년 전",
        "channel_name": "이상호"
    },
    {
        "title": "4억 올금카 곽준혁 VS 700조 본캐 뿌꾸 임유진",
        "views": "조회수 48만회",
        "upload_date": "5개월 전",
        "channel_name": "두치와뿌꾸"
    },
    {
        "title": "피파 실력 1, 2황을 잡은 임유진 폼 미쳤다",
        "views": "조회수 26만회",
        "upload_date": "1년 전",
        "channel_name": "임유진"
    },
    {
        "title": "레알VS바르샤 임유진과 드디어 엘클 붙었다!",
        "views": "조회수 10만회",
        "upload_date": "3주 전",
        "channel_name": "두치와뿌꾸"
    },
    {
        "title": "복귀 했으니까 일단 피파 반장 자리부터 뺏겠습니다",
        "views": "조회수 10만회",
        "upload_date": "9개월 전",
        "channel_name": "임유진"
    },
    {
        "title": "둘이 먹다 둘 다 죽는 콩나물 불고기",
        "views": "조회수 10만회",
        "upload_date": "1년 전",
        "channel_name": "임유진"
    },
    {
        "title": "임유진 방송 역사상 최대의 위기",
        "views": "조회수 1.4만회",
        "upload_date": "4개월 전",
        "channel_name": "훈이형 Hun2bro"
    },
    {
        "title": "20만원으로 1조 먹은 사람.. 정무형 크리스마스 선물이야?",
        "views": "조회수 13만회",
        "upload_date": "8개월 전",
        "channel_name": "임유진"
    },
    {
        "title": "뿌드컵 네덜란드 임유진이 4:1로 이길 수 있었던 이유 | 피파4",
        "views": "조회수 2.9만회",
        "upload_date": "1년 전",
        "channel_name": "Official 섭이 S2 FConline KOR"
    },
    {
        "title": "신규 빠칭코 47배..? 본캐에서 쓰던 선수도 떴다!!!",
        "views": "조회수 14만회",
        "upload_date": "1년 전",
        "channel_name": "임유진"
    },
    {
        "title": "피파 시작한 지 2년 만에 슈퍼 챌린저에 왔습니다",
        "views": "조회수 16만회",
        "upload_date": "7개월 전",
        "channel_name": "임유진"
    },
    {
        "title": "비닐신과의 작별로 인해 머리를 잘랐습니다..",
        "views": "조회수 19만회",
        "upload_date": "11개월 전",
        "channel_name": "임유진"
    },
    {
        "title": "뿌챔스 김민교에게 4:0으로 지고 광탈한 그녀의 술먹방..",
        "views": "조회수 17만회",
        "upload_date": "1년 전",
        "channel_name": "임유진"
    },
    {
        "title": "깐족 피파의 제왕 방배우 임유진을 무너뜨리다 FC온라인",
        "views": "조회수 1.5만회",
        "upload_date": "2개월 전",
        "channel_name": "방배우"
    },
    {
        "title": "패치 이후 실력이 떡상해버린 상나라의 장군 임유진..?",
        "views": "조회수 21만회",
        "upload_date": "1년 전",
        "channel_name": "임유진"
    },
    {
        "title": "나와 함께 하소서 Abide With Me [Korean Version] - 임유진 Yoojin Lim",
        "views": "조회수 2.2만회",
        "upload_date": "9년 전",
        "channel_name": "Artists United 아티스트 유나이티드"
    },
    {
        "title": "2000억 올금카 방배우 VS 1500조 뿌꾸 임유진 본캐",
        "views": "조회수 12만회",
        "upload_date": "2개월 전",
        "channel_name": "두치와뿌꾸"
    },
    {
        "title": "포를란에게 빠진 나머지 3조 6천억 인테르로 팀갈해버렸습니다",
        "views": "조회수 35만회",
        "upload_date": "1년 전",
        "channel_name": "임유진"
    },
    {
        "title": "새벽 2시에 임유진이랑 삼겹살 먹방!! [ Pork Mukbang ]",
        "views": "조회수 8.9만회",
        "upload_date": "10개월 전",
        "channel_name": "마빡"
    },
    {
        "title": "공보다 입으로 먼저 골을 넣는다 김민교 vs 임유진 feat.강만식,상윤 2022.3.9 풀영상",
        "views": "조회수 1.8만회",
        "upload_date": "2년 전",
        "channel_name": "튜브김민교 풀영상"
    },
    {
        "title": "임유진 너 많이 늘었다?",
        "views": "조회수 9.8만회",
        "upload_date": "7개월 전",
        "channel_name": "울산큰고래 박성주"
    },
    {
        "title": "본캐 2조 토티 단일팀 맞췄습니다!! 쏘니와 덕배를 동시에..?",
        "views": "조회수 38만회",
        "upload_date": "1년 전",
        "channel_name": "임유진"
    },
    {
        "title": "임유진 도발에 못참고 결국...",
        "views": "조회수 1.6천회",
        "upload_date": "1년 전",
        "channel_name": "훈이형 Hun2bro"
    },
    {
        "title": "어김없이 전화해서 불렀다.. 임유진vs김민교 feat.우질,스카우터,뿌꾸 2022.8.12 풀영상",
        "views": "조회수 1.6만회",
        "upload_date": "2년 전",
        "channel_name": "튜브김민교 풀영상"
    },
    {
        "title": "임유진이랑 피파끝나고 먹방하는데 설렜습니다...?! [ Mukbang ]",
        "views": "조회수 14만회",
        "upload_date": "1년 전",
        "channel_name": "마빡"
    },
    {
        "title": "임유진성공스토리",
        "views": "조회수 1.1천회",
        "upload_date": "9년 전",
        "channel_name": "임유진"
    },
    {
        "title": "서버 1위 250조 리버풀을 써봤더니ㄷㄷ.. 리버풀 마렵네요",
        "views": "조회수 17만회",
        "upload_date": "8개월 전",
        "channel_name": "임유진"
    },
    {
        "title": "피자집 아들 앞에서 피자 만들기 (feat. 믹슈)",
        "views": "조회수 12만회",
        "upload_date": "10개월 전",
        "channel_name": "임유진"
    },
    {
        "title": "[한국컴패션] 임유진 후원자 이야기",
        "views": "조회수 1.3천회",
        "upload_date": "13년 전",
        "channel_name": "컴패션 CompassionKR"
    },
    {
        "title": "아무렇지 않게 10카 붙이기",
        "views": "조회수 330만회",
        "upload_date": "1년 전",
        "channel_name": "임유진"
    },
    {
        "title": "무과금으로 맞춰도 너무 좋네요.. | 무과금 부캐 키우기",
        "views": "조회수 22만회",
        "upload_date": "1년 전",
        "channel_name": "임유진"
    },
    {
        "title": "30만원 임유진한테 맡겼더니 35배",
        "views": "조회수 59만회",
        "upload_date": "1년 전",
        "channel_name": "미남홀란드"
    },
    {
        "title": "윤태영 〈왕초〉 비하인드ㅋㅋㅋ 거지3으로 시작한 전설의 맨발🔥 #운탄고도마을호텔2 EP.3 | tvN STORY 230310 방송",
        "views": "조회수 10만회",
        "upload_date": "1년 전",
        "channel_name": "tvN STORY 티비엔 스토리"
    },
    {
        "title": "월드컵 덕배 8카? 400억 윙으로 털어드립니다",
        "views": "조회수 19만회",
        "upload_date": "1년 전",
        "channel_name": "임유진"
    },
    {
        "title": "드록바와 덕배를 들고 찾아간 임유진 리매치 2022.11.26 풀영상",
        "views": "조회수 1만회",
        "upload_date": "1년 전",
        "channel_name": "튜브김민교 풀영상"
    },
    {
        "title": "4조 호날두와 함께 공경 챌린저 찍기!! 근데 몸싸움이..",
        "views": "조회수 17만회",
        "upload_date": "1년 전",
        "channel_name": "임유진"
    },
    {
        "title": "임동진 딸 임예원 임유진 배우 집안",
        "views": "조회수 262회",
        "upload_date": "6년 전",
        "channel_name": "L2 KOREA NEWS"
    },
    {
        "title": "히트 (Heat/임유진) - My Way",
        "views": "조회수 6.2천회",
        "upload_date": "3년 전",
        "channel_name": "wind"
    },
    {
        "title": "임유진의 2조 6천억 토티 벤제마 손흥민",
        "views": "조회수 11만회",
        "upload_date": "1년 전",
        "channel_name": "미남홀란드"
    },
    {
        "title": "팀갈빵 with 교시티",
        "views": "조회수 21만회",
        "upload_date": "1년 전",
        "channel_name": "임유진"
    },
    {
        "title": "[Crossover] 류지광 청년백서 9화 | 임유진 교수님 | 나의 삶, 별이 되어(ft. 결핍의 채움)",
        "views": "조회수 965회",
        "upload_date": "3년 전",
        "channel_name": "Crossover"
    },
    {
        "title": "잘 벌려?  고말숙",
        "views": "조회수 469만회",
        "upload_date": "6년 전",
        "channel_name": "Beautiful Girl"
    },
    {
        "title": "하다하다 이젠 임유진한테도 ..?",
        "views": "조회수 15만회",
        "upload_date": "1년 전",
        "channel_name": "꾸티뉴"
    },
    {
        "title": "두뿌 따운! 우터 따운! 빅윈 따운! 피파 잘 하는 사람 다 나와!!!!!",
        "views": "조회수 11만회",
        "upload_date": "8개월 전",
        "channel_name": "임유진"
    },
    {
        "title": "98년생 피파 BJ끼리 듀엣하면 생기는 일 ㄷㄷ",
        "views": "조회수 660회",
        "upload_date": "3일 전",
        "channel_name": "훈이형 Hun2bro"
    },
    {
        "title": "초대모델MC가수 임유진   비오는남산  - 예천 용궁시장 토요아침장 개장 산과들푸른예술단",
        "views": "조회수 48회",
        "upload_date": "1개월 전",
        "channel_name": "이홍택 TV"
    },
    {
        "title": "임유진 오랜만에 혼내준다.. 피파1:1 2022.10.21 풀영상",
        "views": "조회수 7.5천회",
        "upload_date": "1년 전",
        "channel_name": "튜브김민교 풀영상"
    },
    {
        "title": "때려줘",
        "views": "조회수 87만회",
        "upload_date": "1년 전",
        "channel_name": "케미 모음집"
    },
    {
        "title": "월클기념 피파여캠 서열정리 갈게요 (으네 아띠 임유진)",
        "views": "조회수 3천회",
        "upload_date": "1년 전",
        "channel_name": "써니튜브 sunny_tube"
    },
    {
        "title": "김민교의 애착인형 그녀",
        "views": "조회수 30만회",
        "upload_date": "2년 전",
        "channel_name": "튜브김민교"
    },
    {
        "title": "임유진 아~~~~~~",
        "views": "조회수 2.4만회",
        "upload_date": "11개월 전",
        "channel_name": "마빡"
    },
    {
        "title": "[뿌꾸vs] 철 지난 신림동의 좋밥 노래부르기빵 좋밥 임유진^^",
        "views": "조회수 11만회",
        "upload_date": "8개월 전",
        "channel_name": "두치와뿌꾸"
    },
    {
        "title": "저 호동생 아닙니다",
        "views": "조회수 17만회",
        "upload_date": "1년 전",
        "channel_name": "임유진"
    },
    {
        "title": "유벤투스 수비형 미드필더 끝판왕을 찾았습니다..",
        "views": "조회수 14만회",
        "upload_date": "7개월 전",
        "channel_name": "임유진"
    },
    {
        "title": "신규 패키지 현질하고 급여 240 레알로 리빌딩 했습니다",
        "views": "조회수 26만회",
        "upload_date": "1년 전",
        "channel_name": "임유진"
    },
    {
        "title": "댄서 임유진 르세라핌(LE SSERAFIM) FEARLESS 커버 - 홍대 버스킹 220526",
        "views": "조회수 4.8천회",
        "upload_date": "2년 전",
        "channel_name": "놀이"
    },
    {
        "title": "만남을 위한 이별 Parting for Meeting Again  - 임유진 Yoojin Lim",
        "views": "조회수 1.7천회",
        "upload_date": "10년 전",
        "channel_name": "Artists United 아티스트 유나이티드"
    },
    {
        "title": "가요대전 배호편 #비오는남산 당신 #임유진",
        "views": "조회수 2.5천회",
        "upload_date": "3개월 전",
        "channel_name": "Top가요tv"
    },
    {
        "title": "임유진시구 6월16일(토) 넥센vs롯데",
        "views": "조회수 1.8천회",
        "upload_date": "12년 전",
        "channel_name": "키움히어로즈"
    },
    {
        "title": "유봉훈을 잡고 우질이를 잡은 임유진?",
        "views": "조회수 5.2만회",
        "upload_date": "1년 전",
        "channel_name": "Official 섭이 S2 FConline KOR"
    },
    {
        "title": "나이는 숫자에 불과하다",
        "views": "조회수 14만회",
        "upload_date": "3개월 전",
        "channel_name": "울산큰고래 박성주"
    },
    {
        "title": "24토티 벨링엄이 양발이라구요? 이럴 거면 레알 안 버렸지 정무형..",
        "views": "조회수 17만회",
        "upload_date": "7개월 전",
        "channel_name": "임유진"
    },
    {
        "title": "담배 하루 3~4갑 [뽀구미 클립]",
        "views": "조회수 38만회",
        "upload_date": "1년 전",
        "channel_name": "냉동상어"
    },
    {
        "title": "저 이제부터 맨유 응원하겠습니다! 여러분도 같이..",
        "views": "조회수 18만회",
        "upload_date": "6개월 전",
        "channel_name": "임유진"
    },
    {
        "title": "임유진맘이 된 케이! 임유진 스타 훈련시키기",
        "views": "조회수 3.4천회",
        "upload_date": "2년 전",
        "channel_name": "더케이 풀영상 | The K"
    },
    {
        "title": "뿌꾸 VS 우질 어제까지만 해도 같이 춤추던 사이...진심으로 붙었다 ㅋㅋㅋㅋ",
        "views": "조회수 8.2만회",
        "upload_date": "2개월 전",
        "channel_name": "두치와뿌꾸"
    },
    {
        "title": "피파 시작한 지 1년 만에 드디어 챌린저를 찍었습니다",
        "views": "조회수 25만회",
        "upload_date": "1년 전",
        "channel_name": "임유진"
    },
    {
        "title": "사랑꾼 태영♥ 아내가 굿 샷 하면 기분이 좋아✌️ TV CHOSUN 220611 방송",
        "views": "조회수 3.6만회",
        "upload_date": "2년 전",
        "channel_name": "TVCHOSUN - TV조선"
    },
    {
        "title": "유튜버 임유진의 1조 잉글랜드",
        "views": "조회수 24만회",
        "upload_date": "1년 전",
        "channel_name": "미남홀란드"
    },
    {
        "title": "22챔스 벤제마 금카 VS 모먼트 2명.. 프로게이머도 감탄한 임유진의 경기력!!",
        "views": "조회수 22만회",
        "upload_date": "1년 전",
        "channel_name": "임유진"
    },
    {
        "title": "정들었던 50조 레알.. 다 팔았습니다ㅎㅎ",
        "views": "조회수 21만회",
        "upload_date": "8개월 전",
        "channel_name": "임유진"
    },
    {
        "title": "임유진 성대모사",
        "views": "조회수 36만회",
        "upload_date": "1년 전",
        "channel_name": "주팍갤러리"
    },
    {
        "title": "임유진의 케마토크[부동산블루오션을 찾아라1편]이제문교수님",
        "views": "조회수 225회",
        "upload_date": "4년 전",
        "channel_name": "임대표의랜선부동산"
    },
    {
        "title": "사라진 나의 토츠두 그리고 BWC 호돈 7카 영입.. 미쳐버린 호돈의 DD?!",
        "views": "조회수 16만회",
        "upload_date": "1년 전",
        "channel_name": "임유진"
    },
    {
        "title": "2018 아트위캔 피아노콘서트 임유진 F. Chopin ----- Etude Op.25 No.11",
        "views": "조회수 1.9천회",
        "upload_date": "6년 전",
        "channel_name": "사. 한국발달장애인문화예술협회 아트위캔"
    },
    {
        "title": "가수 임유진   내 생애 최고의 남자 (임유진 타이틀곡)",
        "views": "조회수 1.5천회",
        "upload_date": "5년 전",
        "channel_name": "이홍택 TV"
    },
    {
        "title": "역대급 점수 도달달성 후 그녀에게 전화한통.. feat임유진 피파1:1 2022.7.9 풀영상",
        "views": "조회수 2.6만회",
        "upload_date": "2년 전",
        "channel_name": "튜브김민교 풀영상"
    },
    {
        "title": "내 남자, 노래 너무 좋아요~♡#모델mc가수 #임유진 #원곡 #박나경 #내남자",
        "views": "조회수 102회",
        "upload_date": "8개월 전",
        "channel_name": "임유진TV(대박엔터)"
    },
    {
        "title": "남몰래 흐르는 눈물_ 임유진(사랑의 묘약 중)- 독음- 비익조 사랑",
        "views": "조회수 148회",
        "upload_date": "3년 전",
        "channel_name": "정동기"
    },
    {
        "title": "제가 뮌헨을 떠나겠습니다",
        "views": "조회수 18만회",
        "upload_date": "1년 전",
        "channel_name": "임유진"
    },
    {
        "title": "미친 타격감 임유진.. 또 팬다 feat.뀨알, 꿀탱탱 1:1 2022.3.17 풀영상",
        "views": "조회수 2.3만회",
        "upload_date": "2년 전",
        "channel_name": "튜브김민교 풀영상"
    },
    {
        "title": "서버 단 1장뿐인 24토티 반데이크 금카 '벽 그 자체'를 써봤습니다ㄷㄷ",
        "views": "조회수 17만회",
        "upload_date": "7개월 전",
        "channel_name": "임유진"
    },
    {
        "title": "프랑스 국대 의문의 선수 영입",
        "views": "조회수 6.6만회",
        "upload_date": "1년 전",
        "channel_name": "임유진"
    },
    {
        "title": "임유진 기자 영상",
        "views": "조회수 282회",
        "upload_date": "1년 전",
        "channel_name": "제이제이고고"
    },
    {
        "title": "윤태영 임유진 쌍둥이 자녀 집 집안 아버지",
        "views": "조회수 419회",
        "upload_date": "6년 전",
        "channel_name": "AU GR Entertaiment"
    },
    {
        "title": "50조 팀에 공격진만 40조? 가격 이게 맞나요..",
        "views": "조회수 17만회",
        "upload_date": "8개월 전",
        "channel_name": "임유진"
    },
    {
        "title": "예? 임유진의 메이드복이요?",
        "views": "조회수 12만회",
        "upload_date": "4개월 전",
        "channel_name": "두치와뿌꾸"
    },
    {
        "title": "임유진씨 저희 이제...",
        "views": "조회수 9만회",
        "upload_date": "1년 전",
        "channel_name": "마빡"
    },
    {
        "title": "공식경기 100골 노방종이요..?",
        "views": "조회수 24만회",
        "upload_date": "1년 전",
        "channel_name": "임유진"
    },
    {
        "title": "강등과 연승 사이.. 공식경기 피드백 부탁드립니다 여러분",
        "views": "조회수 11만회",
        "upload_date": "1년 전",
        "channel_name": "임유진"
    },
    {
        "title": "다리 긁기의 맛을 알아버린 임유진의 \"맨유 사용법\"",
        "views": "조회수 11만회",
        "upload_date": "5개월 전",
        "channel_name": "임유진"
    },
    {
        "title": "모델MC가수 임유진 타인 글로벌예술단 가요사랑페스티벌",
        "views": "조회수 201회",
        "upload_date": "1년 전",
        "channel_name": "가요K j미디어기획"
    },
    {
        "title": "우리밍, 임유진 두 여자의 \"호\" 여동생 쟁탈전",
        "views": "조회수 9.7천회",
        "upload_date": "1년 전",
        "channel_name": "우리밍"
    },
    {
        "title": "샤라웃을 듣고 디스랩 하러 온 임유진",
        "views": "조회수 1.5천회",
        "upload_date": "2개월 전",
        "channel_name": "훈이형 Hun2bro"
    },
    {
        "title": "임유진때문에 12연 샷건치는 영상",
        "views": "조회수 8.8천회",
        "upload_date": "1년 전",
        "channel_name": "훈이형 Hun2bro"
    },
    {
        "title": "본캐 1조 2천억 ac밀란 스쿼드 완성",
        "views": "조회수 29만회",
        "upload_date": "1년 전",
        "channel_name": "임유진"
    },
    {
        "title": "[제이톤 실용음악학원]임유진 이동민-숨소리(vocal)",
        "views": "조회수 168회",
        "upload_date": "6년 전",
        "channel_name": "제이톤뮤직"
    },
    {
        "title": "#오라버니  #임유진  #원곡 :금잔디 #날 사랑 하신다 하니 ..   #정말 행복하여서",
        "views": "조회수 28회",
        "upload_date": "5개월 전",
        "channel_name": "TS MusicSongLyrics歌詞노래가사"
    },
    {
        "title": "윤태영 임유진 내조",
        "views": "조회수 3.3천회",
        "upload_date": "2년 전",
        "channel_name": "창녕화왕산경매장(옥션)"
    },
    {
        "title": "렌즈 빼는 임유진",
        "views": "조회수 103회",
        "upload_date": "1년 전",
        "channel_name": "최강유진"
    },
    {
        "title": "남자랑 같이 살 때 힘든 이유 [리플하우스#4 : 임유진 수난시대]",
        "views": "조회수 45만회",
        "upload_date": "2년 전",
        "channel_name": "Ripple_S"
    },
    {
        "title": "5000억 신상 레반과 함께하는 ‘행복’ 피파",
        "views": "조회수 22만회",
        "upload_date": "1년 전",
        "channel_name": "임유진"
    },
    {
        "title": "공포의 강화데이",
        "views": "조회수 6.3만회",
        "upload_date": "1년 전",
        "channel_name": "임유진"
    },
    {
        "title": "폼오른 임유진?! 유치한 그들의 피파대결 2023.3.26 풀영상",
        "views": "조회수 9.1천회",
        "upload_date": "1년 전",
        "channel_name": "튜브김민교 풀영상"
    },
    {
        "title": "[JOY #Shorts] 6언더의 진실 #골프왕 #TV조선조이 #TVCHOSUNJOY (TV CHOSUN 220611 방송)",
        "views": "조회수 35만회",
        "upload_date": "2년 전",
        "channel_name": "TVCHOSUN JOY"
    },
    {
        "title": "임유진한테 폭로당했습니다",
        "views": "조회수 2.7천회",
        "upload_date": "1년 전",
        "channel_name": "훈이형 Hun2bro"
    },
    {
        "title": "[JOY #Shorts] 눈물 많은 사랑꾼 윤태영 #골프왕 #TV조선조이 #TVCHOSUNJOY (TV CHOSUN 220611 방송)",
        "views": "조회수 26만회",
        "upload_date": "2년 전",
        "channel_name": "TVCHOSUN JOY"
    },
    {
        "title": "23.01.28 - YD배드민턴대회 김민재,고은비 VS 남상환,임유진",
        "views": "조회수 56회",
        "upload_date": "1년 전",
        "channel_name": "은비까비"
    },
    {
        "title": "[뿌드컵] 뿌꾸 드디어 출격 임유진을 상대로 만나게 되는데...",
        "views": "조회수 10만회",
        "upload_date": "2주 전",
        "channel_name": "두치와뿌꾸"
    },
    {
        "title": "임유진 어디가!",
        "views": "조회수 5.8만회",
        "upload_date": "1년 전",
        "channel_name": "미남홀란드"
    },
    {
        "title": "벤제마 영입.. 손흥민과 벤제마의 호흡 토티 단일팀",
        "views": "조회수 22만회",
        "upload_date": "1년 전",
        "channel_name": "임유진"
    },
    {
        "title": "임유진 팀완성하자마자 팀갈하게 만들기ㅋㅋㅋㅋ",
        "views": "조회수 7.9만회",
        "upload_date": "1년 전",
        "channel_name": "빅윈TV"
    },
    {
        "title": "모델MC가수 임유진 인연의끈 홍보대사 불꽃연예예술단 2023,송년,가요콘서트",
        "views": "조회수 459회",
        "upload_date": "8개월 전",
        "channel_name": "가요K j미디어기획"
    },
    {
        "title": "내가 너에게 - 임유진 @ 힐링유",
        "views": "조회수 2.7천회",
        "upload_date": "9년 전",
        "channel_name": "CGN"
    },
    {
        "title": "0429 모델MC가수 임유진 엔딩 메들리 #달성토성마을 #축제 #대박엔터 #관중분들과함께 #신나게 #흥 #최고",
        "views": "조회수 959회",
        "upload_date": "1년 전",
        "channel_name": "임유진TV(대박엔터)"
    },
    {
        "title": "【피파4】명심해. 이만큼 넣어야 손흥민 살 수 있다",
        "views": "조회수 9.8만회",
        "upload_date": "2년 전",
        "channel_name": "스맵[Smeb]"
    },
    {
        "title": "[JOY #Shorts] 옛날 사람 윤태영 #골프왕 #TV조선조이 #TVCHOSUNJOY (TV CHOSUN 220611 방송)",
        "views": "조회수 19만회",
        "upload_date": "2년 전",
        "channel_name": "TVCHOSUN JOY"
    },
    {
        "title": "유진아 미안한데 니 팀 구리다",
        "views": "조회수 11만회",
        "upload_date": "1년 전",
        "channel_name": "뀨알Tube"
    },
    {
        "title": "레전드 10카 아무렇지 않게 붙이기 #임유진 #shorts",
        "views": "조회수 1천회",
        "upload_date": "4개월 전",
        "channel_name": "피파주번"
    },
    {
        "title": "10만 피파 유튜버가 짜준 나의 1조 3천억 뮌헨",
        "views": "조회수 29만회",
        "upload_date": "1년 전",
        "channel_name": "임유진"
    },
    {
        "title": "정말 죄송합니다... 임유진 빡종 사건...",
        "views": "조회수 3.4만회",
        "upload_date": "1년 전",
        "channel_name": "빅윈TV"
    },
    {
        "title": "홍대연기학원 서울예대, 경희대, 국민대, 세종대 정시 최종합격자 - 임유진 (서울연기학원,홍대연기학원,합정연기학원,대학입시연기학원,연극영화과,연기과,뮤지컬,배우,연기선생님)",
        "views": "조회수 3천회",
        "upload_date": "5년 전",
        "channel_name": "쓰리에스연기학원"
    },
    {
        "title": "내가 너에게 Telling You  - 임유진 Yoojin Lim",
        "views": "조회수 4.3천회",
        "upload_date": "10년 전",
        "channel_name": "Artists United 아티스트 유나이티드"
    },
    {
        "title": "북대구 가요TV에서 인연의 끈 (디스코버전) 불렀습니다~#임유진 #모델MC가수",
        "views": "조회수 239회",
        "upload_date": "10개월 전",
        "channel_name": "임유진TV(대박엔터)"
    },
    {
        "title": "가수 임유진과 개가수 김청산 듀엣",
        "views": "조회수 1.3천회",
        "upload_date": "1년 전",
        "channel_name": "임유진TV(대박엔터)"
    },
    {
        "title": "Abide With Me 나와 함께 하소서 [English Version]  - 임유진 Yoojin Lim",
        "views": "조회수 2.2천회",
        "upload_date": "9년 전",
        "channel_name": "Artists United 아티스트 유나이티드"
    },
    {
        "title": "임유진 피파온라인 BJ 소개 영상 (BJ 소개 필수)",
        "views": "조회수 123회",
        "upload_date": "1년 전",
        "channel_name": "Dorong_C4D"
    },
    {
        "title": "임유진의 속을 파헤쳐보자",
        "views": "조회수 24만회",
        "upload_date": "2년 전",
        "channel_name": "Ripple_S"
    },
    {
        "title": "[페이머스초롱 BUSKING] 있는 그대로 당신을 (작사/작곡: 임유진) _ 페이머스초롱 @남산타워",
        "views": "조회수 155회",
        "upload_date": "4년 전",
        "channel_name": "페이머스초롱TV"
    },
    {
        "title": "FC온라인 관계자분들, 이 영상을 꼭 봐주세요. #shorts",
        "views": "조회수 69만회",
        "upload_date": "4개월 전",
        "channel_name": "임유진"
    },
    {
        "title": "케이 오지은 공개연애 #shorts",
        "views": "조회수 319만회",
        "upload_date": "1년 전",
        "channel_name": "케이"
    },
    {
        "title": "e-NEWS - Ep.1711 : 유산만 450억! 윤태영, 그의 아버지는?",
        "views": "조회수 4만회",
        "upload_date": "10년 전",
        "channel_name": "CJ ENM"
    },
    {
        "title": "?? : 양쪽 팔꿈치 서로 닿나요?",
        "views": "조회수 1126만회",
        "upload_date": "2년 전",
        "channel_name": "미선짱"
    },
    {
        "title": "교시티 vs 임알 마드리드",
        "views": "조회수 36만회",
        "upload_date": "1년 전",
        "channel_name": "임유진"
    },
    {
        "title": "임유진한테 고소당했습니다",
        "views": "조회수 11만회",
        "upload_date": "1년 전",
        "channel_name": "훈이형 Hun2bro"
    },
    {
        "title": "예감 없이도 미친 듯 꺾이는 포를란 ZD로 공식 경기 챌린저 찍기",
        "views": "조회수 12만회",
        "upload_date": "1년 전",
        "channel_name": "임유진"
    },
    {
        "title": "지금까지 흙유진을 사랑해 주셔서 감사합니다. | 무과금 부캐 키우기",
        "views": "조회수 25만회",
        "upload_date": "1년 전",
        "channel_name": "임유진"
    },
    {
        "title": "윤태영 나이 와이프 부인 아내 임유진 결혼 자녀 가족 고향 집안 재산",
        "views": "조회수 6.4천회",
        "upload_date": "2년 전",
        "channel_name": "배민커넥트추천인 친추 친구 추천 초대 idujh"
    },
    {
        "title": "원곡자 신승태: 사랑불 #임유진  #모델mc가수 #사랑불 #많관부 #좋아요 #구독",
        "views": "조회수 415회",
        "upload_date": "6개월 전",
        "channel_name": "임유진TV(대박엔터)"
    },
    {
        "title": "Nacht und Träume 밤과 꿈 Night and Dream - 임유진 Yoojin Lim",
        "views": "조회수 1.2만회",
        "upload_date": "9년 전",
        "channel_name": "Artists United 아티스트 유나이티드"
    },
    {
        "title": "[오피셜]임유진 훈이형과 뒷결선언??",
        "views": "조회수 4.1천회",
        "upload_date": "1년 전",
        "channel_name": "훈이형 Hun2bro"
    },
    {
        "title": "관객과도 열심히 소통하는 #모델MC가수임유진 #대박엔터 #기찻길축제 #다같이 #흔들어 #신나게",
        "views": "조회수 658회",
        "upload_date": "1년 전",
        "channel_name": "임유진TV(대박엔터)"
    },
    {
        "title": "타이틀곡 내생애 최고의 남자 #모델mc가수 #임유진 #응원 #감사합니다 #더열심히활동하겠습니다 #하트하트",
        "views": "조회수 277회",
        "upload_date": "1년 전",
        "channel_name": "임유진TV(대박엔터)"
    },
    {
        "title": "민교님의 515?! 32조 맨시티+인테르를 만났더니 충격적인 결과가..?",
        "views": "조회수 16만회",
        "upload_date": "1년 전",
        "channel_name": "임유진"
    },
    {
        "title": "샷건 근절 캠페인 1일차",
        "views": "조회수 14만회",
        "upload_date": "1년 전",
        "channel_name": "임유진"
    },
    {
        "title": "팀 맞추고 바로 김민교vs임유진 팀갈빵..? 2022.11.29 풀영상",
        "views": "조회수 1.5만회",
        "upload_date": "1년 전",
        "channel_name": "튜브김민교 풀영상"
    },
    {
        "title": "모델MC가수 임유진 원곡자 배금성 사랑이 비를 맞아요",
        "views": "조회수 429회",
        "upload_date": "1년 전",
        "channel_name": "임유진TV(대박엔터)"
    },
    {
        "title": "디혜유 술주정  #shorts",
        "views": "조회수 1132만회",
        "upload_date": "3년 전",
        "channel_name": "유혜디"
    },
    {
        "title": "초보들이 계약할 때 미리 준비하면 좋은 것들! #임유진 #공인중개사 #중개실무 #Shorts",
        "views": "조회수 110회",
        "upload_date": "2년 전",
        "channel_name": "알아야 돈 번다, 스투언TV - Study to Earn"
    },
    {
        "title": "임유진의 노인 공격",
        "views": "조회수 1만회",
        "upload_date": "6개월 전",
        "channel_name": "국호형"
    },
    {
        "title": "모델mc가수 임유진/고장난 벽시계",
        "views": "조회수 155회",
        "upload_date": "4개월 전",
        "channel_name": "창훈tv"
    },
    {
        "title": "강제 첼시 코인 타게 생겼습니다.. 22챔스",
        "views": "조회수 17만회",
        "upload_date": "1년 전",
        "channel_name": "임유진"
    },
    {
        "title": "임유진의 케마토크[부동산블루오션을 찾아라2편]이제문교수님",
        "views": "조회수 260회",
        "upload_date": "4년 전",
        "channel_name": "임대표의랜선부동산"
    },
    {
        "title": "지는 사람이 탕후루 추기로 했다가 결국...ㅋㅋㅋㅋ",
        "views": "조회수 23만회",
        "upload_date": "3주 전",
        "channel_name": "정준홍"
    },
    {
        "title": "2016 장애인 한마음축제 예술경연대회 임유진 / 피아노",
        "views": "조회수 243회",
        "upload_date": "8년 전",
        "channel_name": "참새TV"
    },
    {
        "title": "임유진 배틀그라운드",
        "views": "조회수 5.8만회",
        "upload_date": "2년 전",
        "channel_name": "임유진"
    },
    {
        "title": "팀 보수공사했습니다.. 2조 리빌딩 뮌헨",
        "views": "조회수 25만회",
        "upload_date": "1년 전",
        "channel_name": "임유진"
    },
    {
        "title": "임유진 윤태영 이혼??  임유진은 오지호와의 결별한 이유. 최근 윤태영의 충격적인 근황. 연예인이슈#35",
        "views": "조회수 6.5천회",
        "upload_date": "2년 전",
        "channel_name": "핫 이슈"
    },
    {
        "title": "롤 영구정지 당한 이유는..?  김민교x임유진 100시간 노방종 풀영상 2022.5.26",
        "views": "조회수 1.8만회",
        "upload_date": "2년 전",
        "channel_name": "튜브김민교 풀영상"
    },
    {
        "title": "artwecan 2014투게더위캔 Piano Concert - 임유진",
        "views": "조회수 916회",
        "upload_date": "9년 전",
        "channel_name": "사. 한국발달장애인문화예술협회 아트위캔"
    },
    {
        "title": "230127 연고전 게스트 임유진 aespa Illusion (에스파 도깨비불) 댄스커버 Dance Cover 직캠 FANCAM /Do",
        "views": "조회수 1.2천회",
        "upload_date": "1년 전",
        "channel_name": "DoDo"
    },
    {
        "title": "피파 칭구들에게 같이 찍어달라고 부탁해 보았다.. #shrots #미스틱 #뀨알 #꾸티뉴 #조경훈 #단아냥 #두치와뿌꾸 #임유진 #피파 #피파온라인4 #mystic",
        "views": "조회수 47만회",
        "upload_date": "1년 전",
        "channel_name": "뀨알Tube"
    },
    {
        "title": "23토티 벤제마 은카로 교체! 2조 5천억 토티 단일팀 진짜 완성",
        "views": "조회수 18만회",
        "upload_date": "1년 전",
        "channel_name": "임유진"
    },
    {
        "title": "6언더 임유진",
        "views": "조회수 98회",
        "upload_date": "2년 전",
        "channel_name": "창녕화왕산경매장(옥션)"
    },
    {
        "title": "우리는 사람이에요 We Are People by 임유진 & 조한신",
        "views": "조회수 1.4천회",
        "upload_date": "9년 전",
        "channel_name": "Artists United 아티스트 유나이티드"
    },
    {
        "title": "왕간다 오빠 차 있어 리액션 보는 임유진 반응 ㅋㅋ",
        "views": "조회수 7천회",
        "upload_date": "1년 전",
        "channel_name": "훈이형 Hun2bro"
    },
    {
        "title": "임유진 패달라해서 갔는데.....",
        "views": "조회수 132회",
        "upload_date": "1년 전",
        "channel_name": "쏭솔"
    },
    {
        "title": "그를 믿지 못한 임유진 결국..",
        "views": "조회수 1.5만회",
        "upload_date": "2년 전",
        "channel_name": "임유진"
    },
    {
        "title": "모델mc초대가수 임유진 = 조약돌 사랑 = 신반 전통시장 한마음 행사 = 주최:신반 전통시장 상인회 = 후원: 의령군 = 원곡 강민",
        "views": "조회수 없음",
        "upload_date": "16시간 전",
        "channel_name": "창훈tv"
    },
    {
        "title": "황금별(뮤지컬 '모차르트!' 中) - 임유진 @ 힐링유",
        "views": "조회수 1.3만회",
        "upload_date": "9년 전",
        "channel_name": "CGN"
    },
    {
        "title": "고래사냥 한다던 임유진의 최후는..?",
        "views": "조회수 9.3만회",
        "upload_date": "1년 전",
        "channel_name": "임유진"
    },
    {
        "title": "임유진이 직접 해준 콩나물 불고기 먹방 [ Bean sprout bulgogi ]",
        "views": "조회수 2.9만회",
        "upload_date": "11개월 전",
        "channel_name": "마빡"
    },
    {
        "title": "윤태영 임유진 골프왕",
        "views": "조회수 116회",
        "upload_date": "2년 전",
        "channel_name": "창녕화왕산경매장(옥션)"
    },
    {
        "title": "예전부터 해왔던 대로 As We Did Before by 임유진 & 조한신",
        "views": "조회수 735회",
        "upload_date": "9년 전",
        "channel_name": "Artists United 아티스트 유나이티드"
    },
    {
        "title": "다같이 신나게 #모델MC가수 #임유진 #타이틀곡 #내생애최고의남자",
        "views": "조회수 96회",
        "upload_date": "1년 전",
        "channel_name": "임유진TV(대박엔터)"
    },
    {
        "title": "피파bj들끼리 풀빌라 여행 가서 삼겹살 먹방하는데 임유진씨...?! [ Samgyupsal Mukbang ]",
        "views": "조회수 11만회",
        "upload_date": "1년 전",
        "channel_name": "마빡"
    },
    {
        "title": "모델MC가수 임유진 _신사랑고개(금잔디)#수성구 #오리배 #shorts",
        "views": "조회수 620회",
        "upload_date": "1년 전",
        "channel_name": "임유진TV(대박엔터)"
    },
    {
        "title": "사랑꾼 윤태영 아내 임유진 뇌 수술에 눈물 ...      #윤태영 #shorts",
        "views": "조회수 8천회",
        "upload_date": "3개월 전",
        "channel_name": "MJ Sunny"
    },
    {
        "title": "초보들이 등기부등본 뗄 때 가장 많이 하는 실수! #임유진 #공인중개사 #중개실무 #Shorts",
        "views": "조회수 425회",
        "upload_date": "2년 전",
        "channel_name": "알아야 돈 번다, 스투언TV - Study to Earn"
    },
    {
        "title": "재력가 만나 신분 상승한 여자 연예인들",
        "views": "조회수 37만회",
        "upload_date": "5개월 전",
        "channel_name": "고추밭"
    },
    {
        "title": "[#장민호]17년만에 임유진, 민호특공대라고 고백~",
        "views": "조회수 1.7만회",
        "upload_date": "2년 전",
        "channel_name": "예능나들이TV"
    },
    {
        "title": "임유진한테 본캐 패키지 현질맡겼다!! 믿고있습니다... 피파4",
        "views": "조회수 8.8만회",
        "upload_date": "1년 전",
        "channel_name": "빡겜"
    },
    {
        "title": "캔디바 먹는 임유진",
        "views": "조회수 106회",
        "upload_date": "1년 전",
        "channel_name": "최강유진"
    },
    {
        "title": "댄서 임유진 스테이씨( STAYC) 런투유(RUN2U) 커버 220526",
        "views": "조회수 189회",
        "upload_date": "2년 전",
        "channel_name": "놀이"
    },
    {
        "title": "임유진 개비싼 금카 사자마자 팔게 만들기ㅋㅋㅋㅋ 피파4",
        "views": "조회수 3.1만회",
        "upload_date": "1년 전",
        "channel_name": "빅윈TV"
    },
    {
        "title": "[피파4] 도전하는 자, 받아들이라..(feat. 임유진)",
        "views": "조회수 6.4천회",
        "upload_date": "1년 전",
        "channel_name": "문스타TV"
    },
    {
        "title": "강화는 말이야..",
        "views": "조회수 18만회",
        "upload_date": "1년 전",
        "channel_name": "임유진"
    },
    {
        "title": "내가꿈꾸는천국/임유진 /키즈 CCM",
        "views": "조회수 700회",
        "upload_date": "3년 전",
        "channel_name": "올포로드153"
    },
    {
        "title": "LH 호날두 금카.. 이거 좋다니까요?",
        "views": "조회수 29만회",
        "upload_date": "1년 전",
        "channel_name": "임유진"
    },
    {
        "title": "임유진의 국악 뱃노래",
        "views": "조회수 121회",
        "upload_date": "1년 전",
        "channel_name": "chang duk Park"
    },
    {
        "title": "윤태영 아내 임유진",
        "views": "조회수 282회",
        "upload_date": "2년 전",
        "channel_name": "창녕화왕산경매장(옥션)"
    },
    {
        "title": "230428모델MC가수 임유진 타이틀곡 내생애 최고의 남자 #영천시 #금호음악단 #대박엔터 #타이틀곡",
        "views": "조회수 53회",
        "upload_date": "1년 전",
        "channel_name": "임유진TV(대박엔터)"
    },
    {
        "title": "[세무사 시험] 세무사 2차 시험 2일 전, 임유진세무사의 합격을 위한  준비 방법! 세무사 자격증 합격을 위한 준비와 꿀팁 대방출~",
        "views": "조회수 3.3천회",
        "upload_date": "1개월 전",
        "channel_name": "바른생각 회계사 세무사"
    },
    {
        "title": "한 아이가 울고 있었네 A Girl Is Crying by 임유진 & 조한신",
        "views": "조회수 1.5천회",
        "upload_date": "9년 전",
        "channel_name": "Artists United 아티스트 유나이티드"
    },
    {
        "title": "모델MC가수임유진,내 생애 최고의 남자,뉴스타가요대행진,대경예술단.2023 04 28",
        "views": "조회수 183회",
        "upload_date": "1년 전",
        "channel_name": "쇼스타TV장감독"
    },
    {
        "title": "숨은 그림 The Hidden Picture by 임유진 & 조한신",
        "views": "조회수 1.8천회",
        "upload_date": "9년 전",
        "channel_name": "Artists United 아티스트 유나이티드"
    },
    {
        "title": "피파 중 급똥..?  김민교vs임유진 피파 2022.9.29 풀영상",
        "views": "조회수 1.6만회",
        "upload_date": "1년 전",
        "channel_name": "튜브김민교 풀영상"
    },
    {
        "title": "모델MC가수 임유진 어버이날 기념 한마음 효잔치 다녀왔어요",
        "views": "조회수 567회",
        "upload_date": "1년 전",
        "channel_name": "임유진TV(대박엔터)"
    },
    {
        "title": "라베 77 임유진 골프왕",
        "views": "조회수 351회",
        "upload_date": "2년 전",
        "channel_name": "창녕화왕산경매장(옥션)"
    },
    {
        "title": "모델mc가수 임유진=당신=원곡 배호",
        "views": "조회수 133회",
        "upload_date": "3개월 전",
        "channel_name": "창훈tv"
    },
    {
        "title": "아름다운 배경과 함께 듣는 #모델mc가수 #임유진 #타이틀곡 내생애 최고의 남자! #많관부 #구독 #좋아요",
        "views": "조회수 6회",
        "upload_date": "5개월 전",
        "channel_name": "임유진TV(대박엔터)"
    },
    {
        "title": "세계의 주인공 King of the World by 임유진 & 조한신",
        "views": "조회수 1.1천회",
        "upload_date": "9년 전",
        "channel_name": "Artists United 아티스트 유나이티드"
    },
    {
        "title": "투명인간 The Invisible by 임유진 & 조한신",
        "views": "조회수 1.5천회",
        "upload_date": "9년 전",
        "channel_name": "Artists United 아티스트 유나이티드"
    },
    {
        "title": "(가수 임유진) 타이틀곡: 내생에 최고의남자",
        "views": "조회수 124회",
        "upload_date": "2년 전",
        "channel_name": "가요나라"
    },
    {
        "title": "EULITE (intro) _ 임유진",
        "views": "조회수 73회",
        "upload_date": "9년 전",
        "channel_name": "임유진"
    },
    {
        "title": "모델가수 임유진 /내 생애 최고의 남자/ 향기 예술 공연단 /정월 대보름 축제",
        "views": "조회수 26회",
        "upload_date": "2년 전",
        "channel_name": "강뭉치"
    },
    {
        "title": "비니시우스 빼고 이 선수 영입했더니 레전드..",
        "views": "조회수 29만회",
        "upload_date": "1년 전",
        "channel_name": "임유진"
    },
    {
        "title": "2년을 기다린 김민교 소개팅에 깜짝 등장한 그녀",
        "views": "조회수 83만회",
        "upload_date": "1개월 전",
        "channel_name": "튜브김민교"
    },
    {
        "title": "가수 임유진(모델종합대상 진 출신)♬내생의최고의남자★대한민국예술문화대상 수상★주관☞스타우드신문사 매거진▶2021년8월",
        "views": "조회수 82회",
        "upload_date": "3년 전",
        "channel_name": "향토TV Korean Traditional songs"
    },
    {
        "title": "크로아티아로 팀갈한 김민교 교스터콜 임유진!  2022.11.16 풀영상",
        "views": "조회수 1.4만회",
        "upload_date": "1년 전",
        "channel_name": "튜브김민교 풀영상"
    },
    {
        "title": "임유진 - 메들리",
        "views": "조회수 208회",
        "upload_date": "5년 전",
        "channel_name": "OJY미디어"
    },
    {
        "title": "본캐 400만원 현질하고 톱 SPL 페리시치 금카 영입..!!",
        "views": "조회수 20만회",
        "upload_date": "1년 전",
        "channel_name": "임유진"
    },
    {
        "title": "가수 임유진-주말에 뭐하세요 [봄맞이힐링콘서트] #스타강사이영재TV #행사섭외01071935092",
        "views": "조회수 157회",
        "upload_date": "5개월 전",
        "channel_name": "영스타 이영재TV (수.목.밤8시 사랑의마술사)"
    },
    {
        "title": "찐친들끼리 대회를?[미남홀란드x임유진x훈이형]",
        "views": "조회수 5.8천회",
        "upload_date": "1년 전",
        "channel_name": "훈이형 Hun2bro"
    },
    {
        "title": "뿌꾸 임유진 제대로 긁었다 ㅋㅋㅋㅋㅋ",
        "views": "조회수 8.1만회",
        "upload_date": "2개월 전",
        "channel_name": "두치와뿌꾸"
    },
    {
        "title": "3000억인데 레전드 성능을 가지고 있는 선수를 아십니까?",
        "views": "조회수 14만회",
        "upload_date": "10개월 전",
        "channel_name": "임유진"
    },
    {
        "title": "임유진 New Diamond 입성식",
        "views": "조회수 1.4천회",
        "upload_date": "11년 전",
        "channel_name": "5927177"
    },
    {
        "title": "[JOY BOX] 역대급 어프로치 친 김민종부터 티샷 238m 친 백돌이 희망 김지석까지!! 역대급 쫄깃~한 대결! #골프왕 #TV조선조이 (TV CHOSUN 220611 방송)",
        "views": "조회수 8만회",
        "upload_date": "2년 전",
        "channel_name": "TVCHOSUN JOY"
    },
    {
        "title": "‘직접 만든‘ 신규시즌 베르캄프 공경에서 써봤는데..",
        "views": "조회수 13만회",
        "upload_date": "1년 전",
        "channel_name": "임유진"
    },
    {
        "title": "연하남에게 고백 받았습니다",
        "views": "조회수 7.4만회",
        "upload_date": "1년 전",
        "channel_name": "임유진"
    },
    {
        "title": "임유진 기자 2022년 10월 영상",
        "views": "조회수 137회",
        "upload_date": "1년 전",
        "channel_name": "제이제이고고"
    },
    {
        "title": "[양평군] 양평음악협회 온라인 공연 - 챔피언스 (sop.장효원/임유진/강남희/남인희)",
        "views": "조회수 735회",
        "upload_date": "4년 전",
        "channel_name": "양평톡톡"
    },
    {
        "title": "(ko)암 면역과 방사선 치료, 그 희망에 대하여 | 임유진 경희대학교 의과대학 조교수 | 건강 의학 항암 | 세바시 1272회",
        "views": "조회수 5.1만회",
        "upload_date": "3년 전",
        "channel_name": "세바시 강연 Sebasi Talk"
    },
    {
        "title": "임유진의 타이틀곡 '주말에 뭐하세요' #모델mc가수 #임유진 #많관부 #많사부 #많은사랑부탁드립니다",
        "views": "조회수 59회",
        "upload_date": "7개월 전",
        "channel_name": "임유진TV(대박엔터)"
    },
    {
        "title": "윤태영음주운전,윤태영나이 집안 재산 그리고 윤태영 결혼 임유진에 대해",
        "views": "조회수 282회",
        "upload_date": "6년 전",
        "channel_name": "KOREAN DAILY News"
    },
    {
        "title": "복귀한 꾸티뉴의 무지성 ZD에 멘탈 나간 임유진ㅋㅋㅋㅋㅋ",
        "views": "조회수 25만회",
        "upload_date": "1년 전",
        "channel_name": "꾸티뉴"
    },
    {
        "title": "흙상호 출격! 100억 계정으로 혼쭐 내드림 [아띠,임유진,섭이] 23.01.06",
        "views": "조회수 3.2천회",
        "upload_date": "1년 전",
        "channel_name": "길게 보는 이상호"
    },
    {
        "title": "72조 첼시요..? 아이콘 굴리트 7카?! | 뿌챔스 프리뷰",
        "views": "조회수 18만회",
        "upload_date": "1년 전",
        "channel_name": "임유진"
    },
    {
        "title": "임유진과 디진다돈까스 데이트",
        "views": "조회수 6.4천회",
        "upload_date": "1년 전",
        "channel_name": "훈이형 Hun2bro"
    },
    {
        "title": "중앙유치원 다나반임유진",
        "views": "조회수 39회",
        "upload_date": "7년 전",
        "channel_name": "은솔유튜브"
    },
    {
        "title": "돌아온 무과금 부캐 키우기..! 100억 팀으로 월클 찍어보겠습니다",
        "views": "조회수 11만회",
        "upload_date": "1년 전",
        "channel_name": "임유진"
    },
    {
        "title": "소개팅 상대가 임유진이라면?",
        "views": "조회수 4.6천회",
        "upload_date": "1년 전",
        "channel_name": "훈이형 Hun2bro"
    },
    {
        "title": "2015 행복발리 임유진",
        "views": "조회수 28회",
        "upload_date": "8년 전",
        "channel_name": "임유진"
    },
    {
        "title": "인공지능과 기계학습 숙명여자대학교 임유진 교수",
        "views": "조회수 285회",
        "upload_date": "1년 전",
        "channel_name": "빅데이터 혁신융합대학"
    },
    {
        "title": "32PROJECT10. 32강 5경기 - 오다정 VS 임유진",
        "views": "조회수 37회",
        "upload_date": "7년 전",
        "channel_name": "어스퀘이크"
    },
    {
        "title": "뿌꾸님께 200만원빵을 지고 술을 먹게 된 슬픈 이야기..",
        "views": "조회수 8.7만회",
        "upload_date": "8개월 전",
        "channel_name": "임유진"
    },
    {
        "title": "임유진 코카인 보고 웃음을 참아야되는 스카우터와 훈이형 ㅋㅋㅋ",
        "views": "조회수 1.8천회",
        "upload_date": "2주 전",
        "channel_name": "훈이형 Hun2bro"
    },
    {
        "title": "임유진2",
        "views": "조회수 23회",
        "upload_date": "11년 전",
        "channel_name": "100억"
    },
    {
        "title": "하루 만에 100레벨 찍는 무과금 RPG 게임이요? [히어로랜드]",
        "views": "조회수 1.2만회",
        "upload_date": "2개월 전",
        "channel_name": "임유진"
    },
    {
        "title": "오늘은 슈챌 갑니다",
        "views": "조회수 11만회",
        "upload_date": "11개월 전",
        "channel_name": "임유진"
    },
    {
        "title": "한편의 드라마.. 아이콘 펠레 2카로 은카 만들기",
        "views": "조회수 15만회",
        "upload_date": "1년 전",
        "channel_name": "임유진"
    },
    {
        "title": "1:1 피파 숙제비 300만원빵 김민교x이상호x임유진 족발한끼 2022.10.26 풀영상",
        "views": "조회수 2.6만회",
        "upload_date": "1년 전",
        "channel_name": "튜브김민교 풀영상"
    },
    {
        "title": "여행가서 임유진한테 고백했는데....",
        "views": "조회수 9.7천회",
        "upload_date": "1년 전",
        "channel_name": "훈이형 Hun2bro"
    },
    {
        "title": "[Into the 교수님] 임유진 교수님 | 20세기 눈송이 vs 21세기 눈송이, 과연 승자가 된 눈송이는?",
        "views": "조회수 518회",
        "upload_date": "3년 전",
        "channel_name": "숙명여대 인공지능공학부 All about AI"
    },
    {
        "title": "중거리 슛 138..? 콜라로프의 미친 ZD",
        "views": "조회수 13만회",
        "upload_date": "1년 전",
        "channel_name": "임유진"
    },
    {
        "title": "그 크신 하나님의 사랑 (The Love Of God) - 임유진",
        "views": "조회수 327회",
        "upload_date": "1년 전",
        "channel_name": "CCMHUB Official"
    },
    {
        "title": "모델 MC 가수 임유진 / 내생애 최고의 남자/한국전통가요협회 트로트페스티벌 /코오롱야외음악당",
        "views": "조회수 36회",
        "upload_date": "2년 전",
        "channel_name": "한국방송연예스타TV ( PD 영상작가 김성재)"
    },
    {
        "title": "모델mc가수 임유진/의령 사랑 음악회/한 많은 대동강/원곡 손인호",
        "views": "조회수 79회",
        "upload_date": "2년 전",
        "channel_name": "창훈tv"
    },
    {
        "title": "230429 모델MC가수 임유진 한많은대동강 #대박엔터 #달성토성마을 #축제 #우윳빛깔 #응원 #감사합니다",
        "views": "조회수 221회",
        "upload_date": "1년 전",
        "channel_name": "임유진TV(대박엔터)"
    },
    {
        "title": "피파월클 렙업을 향해.. + 케이vs임유진 피파대결",
        "views": "조회수 3천회",
        "upload_date": "2년 전",
        "channel_name": "더케이 풀영상 | The K"
    },
    {
        "title": "[오피셜]임유진이 드디어..?",
        "views": "조회수 1.6천회",
        "upload_date": "1년 전",
        "channel_name": "훈이형 Hun2bro"
    },
    {
        "title": "임유진 피아노 대상곡",
        "views": "조회수 232회",
        "upload_date": "8년 전",
        "channel_name": "스마일월드"
    },
    {
        "title": "초대가수 임유진. 인연의끈",
        "views": "조회수 749회",
        "upload_date": "5개월 전",
        "channel_name": "소대장 노래찾아 삼만리"
    },
    {
        "title": "상위 1% 재벌과 결혼한 연예인",
        "views": "조회수 2.7천회",
        "upload_date": "7일 전",
        "channel_name": "keep going"
    },
    {
        "title": "댄서 임유진 블랙핑크(BLACKPINK)의 럽식걸(Lovesick Girls) 커버 220526",
        "views": "조회수 713회",
        "upload_date": "2년 전",
        "channel_name": "놀이"
    },
    {
        "title": "전쟁을 선포합니다 | 삼국지 전략판",
        "views": "조회수 1.2만회",
        "upload_date": "1년 전",
        "channel_name": "임유진"
    },
    {
        "title": "두 번째 New 멤버 고수가 아닌 전설의 초고수 ‘윤태영’ TV CHOSUN 220409 방송  | [골프왕3] 1회  | TV조선",
        "views": "조회수 2.9만회",
        "upload_date": "2년 전",
        "channel_name": "TVCHOSUN - TV조선"
    },
    {
        "title": "고백 - 양다일 COVER vocal임유진 [빌리풀리 정기공연]   송파구실용음악학원 / 방이동실용음악학원",
        "views": "조회수 84회",
        "upload_date": "4년 전",
        "channel_name": "빌리풀리실용음악학원"
    },
    {
        "title": "The ZD vs The DD",
        "views": "조회수 2만회",
        "upload_date": "1년 전",
        "channel_name": "임유진"
    },
    {
        "title": "피파4 임유진님과 레전드 빠칭코 40배 이득!",
        "views": "조회수 2.4천회",
        "upload_date": "1년 전",
        "channel_name": "카토 KATO"
    },
    {
        "title": "사랑의 찬가 - 임유진 / 영상뮤직 / 가사자막",
        "views": "조회수 471회",
        "upload_date": "10개월 전",
        "channel_name": "노래와 시의 풍경"
    },
    {
        "title": "임유진 누나 사랑합니다 #임유진",
        "views": "조회수 582회",
        "upload_date": "1년 전",
        "channel_name": "SENBI (센비)"
    },
    {
        "title": "S전자 부회장 아들 로열패밀리 윤태영과 아내 임유진과의 부러운 이야기",
        "views": "조회수 1.9만회",
        "upload_date": "1년 전",
        "channel_name": "놀튜브"
    },
    {
        "title": "임유진 기자 2023년 4월 영상",
        "views": "조회수 115회",
        "upload_date": "1년 전",
        "channel_name": "제이제이고고"
    },
    {
        "title": "피파 챌린저 달성 실패 벌칙 수행 (feat. 디진다 돈까스)",
        "views": "조회수 17만회",
        "upload_date": "1년 전",
        "channel_name": "임유진"
    },
    {
        "title": "아이즈원 - Sequence 43초! (cover by 임유진)",
        "views": "조회수 169회",
        "upload_date": "3년 전",
        "channel_name": "Magician J."
    },
    {
        "title": "모델mc가수 임유진/타인/원곡 신정수",
        "views": "조회수 52회",
        "upload_date": "2년 전",
        "channel_name": "창훈tv"
    },
    {
        "title": "신규 빠칭코 배율 미쳤는데? #shorts",
        "views": "조회수 37만회",
        "upload_date": "8일 전",
        "channel_name": "임유진"
    },
    {
        "title": "임유진 FS 20091219 꿈나무대회 2급 (영훈초3)",
        "views": "조회수 272회",
        "upload_date": "14년 전",
        "channel_name": "jewelskaters"
    },
    {
        "title": "비비각시(한복쇼)박나경,임유진,김란이,이정아,류재희",
        "views": "조회수 229회",
        "upload_date": "2년 전",
        "channel_name": "창훈tv"
    },
    {
        "title": "모델MC가수 임유진=비오는 남산=원곡 배호",
        "views": "조회수 527회",
        "upload_date": "3개월 전",
        "channel_name": "창훈tv"
    },
    {
        "title": "한반두 넣고 대한민국 맞춰서 행복 피파 했습니다 ㅋㅋㅋㅋ",
        "views": "조회수 14만회",
        "upload_date": "4일 전",
        "channel_name": "정준홍"
    },
    {
        "title": "타이틀곡 내생애 최고의 남자 #모델mc가수 #임유진 #현수막 #응원 #최고 #멋져요 #감사합니다",
        "views": "조회수 341회",
        "upload_date": "1년 전",
        "channel_name": "임유진TV(대박엔터)"
    },
    {
        "title": "임유진x훈이형 커플 솜사탕",
        "views": "조회수 1.5만회",
        "upload_date": "1년 전",
        "channel_name": "훈이형 Hun2bro"
    },
    {
        "title": "24시간 첫번째 여게스트 임유진과 술먹방",
        "views": "조회수 1.8만회",
        "upload_date": "2년 전",
        "channel_name": "더케이 풀영상 | The K"
    },
    {
        "title": "[GFM 가요톡톡] 최상아 & 김시아 초대가수 :김란이,임유진",
        "views": "조회수 153회",
        "upload_date": "3년 전",
        "channel_name": "관악FM"
    },
    {
        "title": "최신 공식경기 금카 공격수 티어리스트 (With 임유진)",
        "views": "조회수 8.5만회",
        "upload_date": "5개월 전",
        "channel_name": "스카우터"
    },
    {
        "title": "트롯견 LET's go! #모델 #mc #가수 #임유진 님과 함께",
        "views": "조회수 293회",
        "upload_date": "5개월 전",
        "channel_name": "흥부자 청산씨"
    },
    {
        "title": "역시 골프왕 맏형! 두 번 만에 온그린 한 윤태영❤ TV CHOSUN 220618 방송 | [골프왕3] 11회  | TV조선",
        "views": "조회수 2.7만회",
        "upload_date": "2년 전",
        "channel_name": "TVCHOSUN - TV조선"
    },
    {
        "title": "모먼트가 기대되는 아이콘 카카로 서열 정리 똑바로 해줬습니다",
        "views": "조회수 14만회",
        "upload_date": "1년 전",
        "channel_name": "임유진"
    },
    {
        "title": "4조 AS로마와 만난 임유진 | 뿌챔스 조추첨",
        "views": "조회수 12만회",
        "upload_date": "1년 전",
        "channel_name": "임유진"
    },
    {
        "title": "ㄱㅇㄹ 설렁탕 먹으면서 복귀! feat.피파 임유진1:1 2022.5.14 풀영상",
        "views": "조회수 1.1만회",
        "upload_date": "2년 전",
        "channel_name": "튜브김민교 풀영상"
    },
    {
        "title": "모델MC가수 임유진, 타이틀곡 내생애 최고의 남자~ #많관부 #행사 #엔터테인먼트",
        "views": "조회수 177회",
        "upload_date": "8개월 전",
        "channel_name": "임유진TV(대박엔터)"
    },
    {
        "title": "#비슬노래방  가수 #윤아 #배훈라 #임유진 편1부 #sbc방송tv/ kpop/k-pop/ktrot/k-trot/메들리/뽕짝/달구벌인가요/가요tv/올겐/관광메들리/라이브/노래방",
        "views": "조회수 283회",
        "upload_date": "스트리밍 시간: 2년 전",
        "channel_name": "Top가요tv"
    },
    {
        "title": "모델가수 임유진   추억의소야곡 - 연꽃사랑음악회 가요페스티벌",
        "views": "조회수 97회",
        "upload_date": "2년 전",
        "channel_name": "이홍택 TV"
    },
    {
        "title": "모델mc가수 임유진/사랑님/대경예술단/원곡 김용임",
        "views": "조회수 112회",
        "upload_date": "2년 전",
        "channel_name": "창훈tv"
    },
    {
        "title": "동백 아가씨 / 모델가수 임유진 / 고령군민을 위한 페스티벌 / 고령대가야시장 / 한국전통가요협회",
        "views": "조회수 45회",
        "upload_date": "2년 전",
        "channel_name": "한국방송연예스타TV ( PD 영상작가 김성재)"
    },
    {
        "title": "뿌챔스 광탈을 위로하는 임유진",
        "views": "조회수 1만회",
        "upload_date": "1년 전",
        "channel_name": "훈이형 Hun2bro"
    },
    {
        "title": "왔구나 나의 장난감  김민교 vs 임유진  김민교의 솔랭! 2023.2.22 풀영상",
        "views": "조회수 1.4만회",
        "upload_date": "1년 전",
        "channel_name": "튜브김민교 풀영상"
    },
    {
        "title": "⚘️가수/고광채 (주말에뭐하세요)원곡임유진♡가요사랑고회장",
        "views": "조회수 357회",
        "upload_date": "1년 전",
        "channel_name": "가요사랑고회장"
    },
    {
        "title": "#singer 국민가수페스티벌 모델🫒MC🫒가수임유진",
        "views": "조회수 8회",
        "upload_date": "2년 전",
        "channel_name": "김영태TY"
    },
    {
        "title": "F.Liszt - Transcendental Etude 4 'Mazeppa' (임유진)",
        "views": "조회수 1만회",
        "upload_date": "5년 전",
        "channel_name": "위드피아노"
    },
    {
        "title": "가수 임유진 {주말에 뭐하세요} 인기가요 스타쇼 초대가수 2019 11 23",
        "views": "조회수 126회",
        "upload_date": "4년 전",
        "channel_name": "기운기TV{데뷔곡}달려라 오늘도🛴"
    },
    {
        "title": "8월 4일 오늘의 말씀 임유진 간사",
        "views": "조회수 123회",
        "upload_date": "3년 전",
        "channel_name": "ᄏᄏᄏTV"
    },
    {
        "title": "임유진 기자 오프닝엔딩 영상",
        "views": "조회수 409회",
        "upload_date": "1년 전",
        "channel_name": "제이제이고고"
    },
    {
        "title": "『완주의 사계』  임유진×미네아트 공연실황 예술극장 숨",
        "views": "조회수 3.5천회",
        "upload_date": "1년 전",
        "channel_name": "예림컴퍼니 / 미네아트"
    },
    {
        "title": "20220526 홍대 (hongdae busking) 유투버,틱톡커(임유진) 친한 지인들과 함께 버스킹 06 - (재희) NMIXX \"O.O\"",
        "views": "조회수 772회",
        "upload_date": "2년 전",
        "channel_name": "dongsub jin"
    },
    {
        "title": "'골프왕3' 윤태영 임유진, 장민호 정동원, 두바이 출국 전날 셀프카메라 공개",
        "views": "조회수 777회",
        "upload_date": "2년 전",
        "channel_name": "스페셜타임스"
    },
    {
        "title": "바로 뽑아버렸습니다ㅋㅋㅋ | 삼국지 전략판",
        "views": "조회수 2.2만회",
        "upload_date": "1년 전",
        "channel_name": "임유진"
    },
    {
        "title": "모델mc초대가수 임유진=사랑 불=칠이회 하계 동창회=원곡 신승태",
        "views": "조회수 475회",
        "upload_date": "3개월 전",
        "channel_name": "창훈tv"
    },
    {
        "title": "박주영 7카 강화했는데..",
        "views": "조회수 29만회",
        "upload_date": "1년 전",
        "channel_name": "임유진"
    },
    {
        "title": "1년간의 성형수술 대공사#Shorts",
        "views": "조회수 1132만회",
        "upload_date": "2년 전",
        "channel_name": "허거덩"
    },
    {
        "title": "대구서구 비산1동 기찻길 축제#shorts #모델MC가수임유진 #메들리 #대박엔터 #신나게",
        "views": "조회수 665회",
        "upload_date": "1년 전",
        "channel_name": "임유진TV(대박엔터)"
    },
    {
        "title": "강만식 오프닝토크x임유진피파합방 레전드빠칭고 300만원x골드문콘서트x봉준 피파레전드 30만개 CKx아카츠키사진전준비 2",
        "views": "조회수 2.8천회",
        "upload_date": "1년 전",
        "channel_name": "강만식 풀영상"
    },
    {
        "title": "임유진, 소개팅 가지마 | [재수파이터] EP.6",
        "views": "조회수 12만회",
        "upload_date": "1년 전",
        "channel_name": "연고티비"
    },
    {
        "title": "이윤우 임유진-토요일 밤에[손담비|Saturday Night] 이윤우 토요일밤에 Saturday Night 최가네봄맞이홍대길거리버스킹 240424 @홍대상상마당",
        "views": "조회수 3.4천회",
        "upload_date": "4개월 전",
        "channel_name": "맛있는솜사탕"
    },
    {
        "title": "에스엠 포핸즈 도전 챌린지 - 임유진 설하윤",
        "views": "조회수 1.3천회",
        "upload_date": "3년 전",
        "channel_name": "에쎔"
    },
    {
        "title": "모델mc가수 임유진/주말에 뭐하세요/작사 이승옥/작곡 정후/노래 임유진",
        "views": "조회수 41회",
        "upload_date": "2년 전",
        "channel_name": "창훈tv"
    },
    {
        "title": "MC모델가수임유진,타인,향기예술공연단,국민가수페스티벌",
        "views": "조회수 86회",
        "upload_date": "2년 전",
        "channel_name": "쇼스타TV장감독"
    },
    {
        "title": "대추🦉경산대추모델가수임유진🫒🫒🫒🫒🫒🫒🫒🫒🫒🫒🫒🫒💯  원곡가수김란이      경산대추🫒부산해운대",
        "views": "조회수 31회",
        "upload_date": "2년 전",
        "channel_name": "김영태TY"
    },
    {
        "title": "이정인 김예빈 임유진 임주현 분석화학 ucc",
        "views": "조회수 198회",
        "upload_date": "5년 전",
        "channel_name": "Kim Tae Hyun"
    },
    {
        "title": "김솔지 임유진 회화 영상",
        "views": "조회수 28회",
        "upload_date": "11년 전",
        "channel_name": "Hugh Le"
    },
    {
        "title": "모델MC 가수 임유진 '인연의 끈' #원곡자 #황진영 #많관부",
        "views": "조회수 860회",
        "upload_date": "1년 전",
        "channel_name": "임유진TV(대박엔터)"
    },
    {
        "title": "강만식 오프닝토크x임유진피파합방 레전드빠칭고 300만원x골드문콘서트x봉준 피파레전드 30만개 CKx아카츠키사진전준비 4",
        "views": "조회수 660회",
        "upload_date": "1년 전",
        "channel_name": "강만식 풀영상"
    },
    {
        "title": "멋진 인생/모델MC가수 임유진/2022 정기총회 및 송년음악회/한국전통가요협회",
        "views": "조회수 84회",
        "upload_date": "1년 전",
        "channel_name": "한국방송연예스타TV ( PD 영상작가 김성재)"
    },
    {
        "title": "피파여신 임유진님이 내방송 팬가입 해주신 날 !!! #피파4 #피파온라인4 #fc온라인 #아프리카tv #YouTube #유튜브 #쇼츠 #Shorts #강화 #돌하르박 #임유진",
        "views": "조회수 284회",
        "upload_date": "3개월 전",
        "channel_name": "돌하르박"
    },
    {
        "title": "가수 임유진☆내생에 최고의 남자 (가사첨부)",
        "views": "조회수 5.4천회",
        "upload_date": "3년 전",
        "channel_name": "홍성주힐링타운"
    },
    {
        "title": "모델MC가수임유진,너는내남자,팔방미인 수성못 사랑의음악회",
        "views": "조회수 104회",
        "upload_date": "2년 전",
        "channel_name": "쇼스타TV장감독"
    },
    {
        "title": "CPU와 배틀쉽게임 with C 신성준161182, 이건희161146, 임유진162086",
        "views": "조회수 56회",
        "upload_date": "7년 전",
        "channel_name": "충남삼성고 IT Dept."
    },
    {
        "title": "2020 1월 EiE 시흥은계 Mid3 1 임유진 Elmo",
        "views": "조회수 7회",
        "upload_date": "4년 전",
        "channel_name": "Jihye Choi"
    },
    {
        "title": "모델가수MC임유진 미운사내 산과들 푸른예술단 제44회 대구약령시 한방문화축제",
        "views": "조회수 52회",
        "upload_date": "1년 전",
        "channel_name": "가요K j미디어기획"
    },
    {
        "title": "모델가수MC임유진 동백아가씨 산과들 푸른예술단 제44회 대구약령시 한방문화축제 월",
        "views": "조회수 52회",
        "upload_date": "1년 전",
        "channel_name": "가요K j미디어기획"
    },
    {
        "title": "모델가수임유진,내생애최고의남자,향기예술공연단 봄이오는소리 가요무대",
        "views": "조회수 232회",
        "upload_date": "2년 전",
        "channel_name": "쇼스타TV장감독"
    },
    {
        "title": "이 팀 나쁘지 않은데...",
        "views": "조회수 25만회",
        "upload_date": "1년 전",
        "channel_name": "두치와뿌꾸"
    },
    {
        "title": "#꿈에   #조덕배   #임유진   #세번째콘서트",
        "views": "조회수 42회",
        "upload_date": "2주 전",
        "channel_name": "yellow submarine"
    },
    {
        "title": "모델mc가수 임유진/가사첨부/대박  엔터테인먼트/내 생애 최고의 남자/작사,작곡 정후/노래 임유진",
        "views": "조회수 221회",
        "upload_date": "1년 전",
        "channel_name": "창훈tv"
    },
    {
        "title": "임유진님과 방대방 대결 골장면 #shorts",
        "views": "조회수 680회",
        "upload_date": "6개월 전",
        "channel_name": "정장남"
    },
    {
        "title": "[한게임섯다] 임유진의 기세",
        "views": "조회수 5.3만회",
        "upload_date": "1개월 전",
        "channel_name": "HANGAME / 한게임"
    },
    {
        "title": "주말에 뭐하세요 / 특별출연 임유진 (2019 곽동우 콘서트)",
        "views": "조회수 57회",
        "upload_date": "4년 전",
        "channel_name": "현봉정수정"
    },
    {
        "title": "모델 MC 가수 임유진 / 추억의 소야곡 / 한국전통가요협회 트로트페스티벌 /코오롱야외음악당",
        "views": "조회수 38회",
        "upload_date": "2년 전",
        "channel_name": "한국방송연예스타TV ( PD 영상작가 김성재)"
    },
    {
        "title": "모델MC가수임유진 단심이 산과들 푸른예술단 제44회 대구약령시 한방문화축제",
        "views": "조회수 54회",
        "upload_date": "1년 전",
        "channel_name": "가요K j미디어기획"
    },
    {
        "title": "임유진의 구독자 10만 축하공연",
        "views": "조회수 3.4천회",
        "upload_date": "1년 전",
        "channel_name": "훈이형 Hun2bro"
    },
    {
        "title": "[성락교회] 전교인 참여미션 - 성락챌린지 참여(임유진) Sungrak Church",
        "views": "조회수 1.3천회",
        "upload_date": "4년 전",
        "channel_name": "성락교회 SUNGRAK CHURCH"
    },
    {
        "title": "본캐 200만 패키지 임유진한테 맡겼는데..",
        "views": "조회수 4.3천회",
        "upload_date": "1년 전",
        "channel_name": "훈이형 Hun2bro"
    },
    {
        "title": "임유진 VS 훈이형 킥드럼베이스",
        "views": "조회수 3.8천회",
        "upload_date": "7개월 전",
        "channel_name": "훈이형 Hun2bro"
    },
    {
        "title": "21챔8카 스털링 영입?!김민교vs스맵,임유진 2022.12.06 풀영상",
        "views": "조회수 1만회",
        "upload_date": "1년 전",
        "channel_name": "튜브김민교 풀영상"
    },
    {
        "title": "동생 다칠까봐 빠르게 달려가는 케이",
        "views": "조회수 60만회",
        "upload_date": "2년 전",
        "channel_name": "반포동강아지"
    },
    {
        "title": "이상호 임유진 카드깡 , 우질과 10만원빵 내기 이후 시연이랑 야외 먹방!!",
        "views": "조회수 1만회",
        "upload_date": "1년 전",
        "channel_name": "길게 보는 이상호"
    },
    {
        "title": "18  임유진",
        "views": "조회수 33회",
        "upload_date": "3년 전",
        "channel_name": "my scene"
    },
    {
        "title": "타이틀곡 주말에 뭐하세요 불러봤어요~ #모델mc가수 #임유진 #타이틀곡 #많관부",
        "views": "조회수 90회",
        "upload_date": "7개월 전",
        "channel_name": "임유진TV(대박엔터)"
    },
    {
        "title": "가수 임유진 //이별의 대구 정거장## 제5회 능금꽃 피는 고향 금호강벚곷길 시민 음악회",
        "views": "조회수 155회",
        "upload_date": "1년 전",
        "channel_name": "c보리수"
    },
    {
        "title": "모델가수임유진,주말에뭐하세요,제20회 경산갓바위 소원성취축제 초대가수,국민연예예술인협회",
        "views": "조회수 48회",
        "upload_date": "2년 전",
        "channel_name": "사단법인 국민연예예술인협회"
    },
    {
        "title": "내생애 최고의 남자(타이틀곡)  가수 임유진",
        "views": "조회수 64회",
        "upload_date": "5년 전",
        "channel_name": "Tv고운"
    },
    {
        "title": "모델가수 임유진/한 많은 대동강/원곡:손인호",
        "views": "조회수 58회",
        "upload_date": "3년 전",
        "channel_name": "창훈tv"
    },
    {
        "title": "임유진양발모아뛰기",
        "views": "조회수 11회",
        "upload_date": "3년 전",
        "channel_name": "김주원 줄넘기"
    },
    {
        "title": "임유진 NCA",
        "views": "조회수 19회",
        "upload_date": "8년 전",
        "channel_name": "임유진"
    },
    {
        "title": "모델MC가수임유진 나비야청산가자 사)한국예총문화예술원&가요TV총국 정기월례회가요사랑",
        "views": "조회수 114회",
        "upload_date": "1년 전",
        "channel_name": "가요K j미디어기획"
    },
    {
        "title": "모델MC가수임유진 님이좋아 사)한국예총문화예술원&가요TV총국 정기월례회가요사랑",
        "views": "조회수 55회",
        "upload_date": "1년 전",
        "channel_name": "가요K j미디어기획"
    },
    {
        "title": "모델MC가수임유진 추억의소야곡 향기예술공연단 2022년펼쳐라내가주인공 가을축제",
        "views": "조회수 52회",
        "upload_date": "1년 전",
        "channel_name": "가요K j미디어기획"
    },
    {
        "title": "모델mc가수 임유진/한국 전통 가요협회/홍도야 울지마라/원곡 김영춘",
        "views": "조회수 82회",
        "upload_date": "1년 전",
        "channel_name": "창훈tv"
    },
    {
        "title": "모짜르트 바이올린협주곡 4번 라장조 1악장 바이올린 임유진 소사벌챔버오케스트라 지휘 김동일 20171017",
        "views": "조회수 562회",
        "upload_date": "6년 전",
        "channel_name": "소사벌챔버오케스트라"
    },
    {
        "title": "2021 가요 대왕전 /가수 임유진 /내 생애 최고의 남자",
        "views": "조회수 40회",
        "upload_date": "2년 전",
        "channel_name": "강뭉치"
    },
    {
        "title": "임유진NCA발리까지",
        "views": "조회수 170회",
        "upload_date": "8년 전",
        "channel_name": "임유진"
    },
    {
        "title": "모델가수임유진,주말에뭐하세요,제6회산과들푸른예술단 가요콘서트",
        "views": "조회수 258회",
        "upload_date": "2년 전",
        "channel_name": "쇼스타TV장감독"
    },
    {
        "title": "초청모델 가수 임유진/서구 파크 골프대회/단심이/원곡 미현",
        "views": "조회수 118회",
        "upload_date": "1년 전",
        "channel_name": "창훈tv"
    },
    {
        "title": "MC모델가수임유진,조약돌사랑,향기엔터테인먼트 봄맞이축제",
        "views": "조회수 384회",
        "upload_date": "1년 전",
        "channel_name": "쇼스타TV장감독"
    },
    {
        "title": "mc가수 주혜령,모델mc가수 임유진/신나게 엔딩",
        "views": "조회수 150회",
        "upload_date": "2년 전",
        "channel_name": "창훈tv"
    },
    {
        "title": "검단신도시아파트 분위기 임유진소장 #검단신도시부동산 #검단신도시아파트 #검단신도시분위기 #검단신도시공인중개사 #임유진의시그널",
        "views": "조회수 598회",
        "upload_date": "1년 전",
        "channel_name": "용감한부동산TV"
    },
    {
        "title": "임유진 기자 2022년 8~9월 영상",
        "views": "조회수 104회",
        "upload_date": "1년 전",
        "channel_name": "제이제이고고"
    },
    {
        "title": "모델가수임유진,내생애최고의남자,향기예술공연단 2022 신년음악회",
        "views": "조회수 218회",
        "upload_date": "2년 전",
        "channel_name": "쇼스타TV장감독"
    },
    {
        "title": "모델MC가수/임유진♬미운사내☞인동남 전국송년음악회☞HIT엔터테인먼트☞ 2022년11월26일",
        "views": "조회수 81회",
        "upload_date": "1년 전",
        "channel_name": "향토TV Korean Traditional songs"
    },
    {
        "title": "모델mc가수 임유진/주말에뭐하세요/원곡 임유진",
        "views": "조회수 261회",
        "upload_date": "3년 전",
        "channel_name": "창훈tv"
    },
    {
        "title": "2017두바이임유진(1)",
        "views": "조회수 86회",
        "upload_date": "7년 전",
        "channel_name": "임유진"
    },
    {
        "title": "임유진 기자 2017년5월~끔찍했던 그날",
        "views": "조회수 90회",
        "upload_date": "1년 전",
        "channel_name": "제이제이고고"
    },
    {
        "title": "임유진 기자 2021년 후반기 영상",
        "views": "조회수 100회",
        "upload_date": "1년 전",
        "channel_name": "제이제이고고"
    },
    {
        "title": "모델MC가수임유진 한많은대동강 산과들푸른예술단 안심제1종합사회복지관 어르신효한마당",
        "views": "조회수 216회",
        "upload_date": "1년 전",
        "channel_name": "가요K j미디어기획"
    },
    {
        "title": "타인👑👑모델 💘가수임유진 한마당음악세상",
        "views": "조회수 113회",
        "upload_date": "2년 전",
        "channel_name": "김영태TV여인가수김란이"
    },
    {
        "title": "달빛음악회👑초청가수임유진",
        "views": "조회수 24회",
        "upload_date": "3년 전",
        "channel_name": "김영태TV여인가수김란이"
    },
    {
        "title": "단계토요장터.매들리커버.모델.가수임유진",
        "views": "조회수 33회",
        "upload_date": "1년 전",
        "channel_name": "김영태TV여인가수김란이"
    },
    {
        "title": "상주페스티벌👑👑 초대가수임유진",
        "views": "조회수 35회",
        "upload_date": "2년 전",
        "channel_name": "김영태TV여인가수김란이"
    },
    {
        "title": "DD 잘 차는 여자 어때요",
        "views": "조회수 8.8만회",
        "upload_date": "1년 전",
        "channel_name": "임유진"
    },
    {
        "title": "중개사도 유튜브로 마케팅해야합니다. _임유진 공인중개사_마케팅/컨설팅 1강 HILIGHT",
        "views": "조회수 1천회",
        "upload_date": "3년 전",
        "channel_name": "공인중개사 빠른합격-메가랜드 땅땅TV"
    },
    {
        "title": "임유진 기자 2022년 11월 영상",
        "views": "조회수 268회",
        "upload_date": "1년 전",
        "channel_name": "제이제이고고"
    },
    {
        "title": "[OST] EP.01 어떻게 - 조잡한파티(feat.임유진)",
        "views": "조회수 153회",
        "upload_date": "2년 전",
        "channel_name": "조잡한파티 / JOJAB Studio"
    },
    {
        "title": "‘골프왕’ 윤태영, 17년 만에 방송 등장한 임유진 향해 “고마워” 눈물",
        "views": "조회수 212회",
        "upload_date": "2년 전",
        "channel_name": "엔터테인먼트 뉴스"
    },
    {
        "title": "현장적발.. #shorts #임유진",
        "views": "조회수 2.3천회",
        "upload_date": "1개월 전",
        "channel_name": "장진호"
    },
    {
        "title": "피온삼국 CK 상나라팀 첫 출격...! [상호X임유진X수야X빅윈X봉훈]",
        "views": "조회수 3.7천회",
        "upload_date": "1년 전",
        "channel_name": "길게 보는 이상호"
    },
    {
        "title": "임유진 기자 2023년 3월 영상",
        "views": "조회수 111회",
        "upload_date": "1년 전",
        "channel_name": "제이제이고고"
    },
    {
        "title": "임유진 실력 왜 이렇게 늘었음?",
        "views": "조회수 214회",
        "upload_date": "1년 전",
        "channel_name": "긴승섭"
    },
    {
        "title": "귀속 + 비싼 호날두 이젠 쓰지 마십쇼!! 방배우 추천 이 선수 주목!! FC온라인",
        "views": "조회수 4.4만회",
        "upload_date": "7일 전",
        "channel_name": "방배우"
    },
    {
        "title": "'넌 센스 퀴즈' 여러분도 맞춰보세요. With 리플 임유진 [티키토크]",
        "views": "조회수 2.4천회",
        "upload_date": "2년 전",
        "channel_name": "갱생끼"
    },
    {
        "title": "임유진 귀엽네...",
        "views": "조회수 13만회",
        "upload_date": "1년 전",
        "channel_name": "마빡"
    },
    {
        "title": "임유진한테 본캐 23토티벤제마 은카맡겼습니다... 피파4",
        "views": "조회수 3.7만회",
        "upload_date": "1년 전",
        "channel_name": "빡겜"
    },
    {
        "title": "모델mc가수 임유진 = 여자의 일생 = 신반 전통시장 한마음 축제 = 원곡 이미자",
        "views": "조회수 없음",
        "upload_date": "13시간 전",
        "channel_name": "창훈tv"
    },
    {
        "title": "임유진 볼살 VS 훈이형 뱃살",
        "views": "조회수 1.8만회",
        "upload_date": "1년 전",
        "channel_name": "훈이형 Hun2bro"
    },
    {
        "title": "[Interview] 아쉬탕가 새벽 마이솔 수련생, 임유진",
        "views": "조회수 1.5천회",
        "upload_date": "2년 전",
        "channel_name": "Tristhana Yoga"
    },
    {
        "title": "케이x야옹민지x민가유x임유진x구보라 개폐급즈 모임",
        "views": "조회수 7.1천회",
        "upload_date": "1년 전",
        "channel_name": "더케이 풀영상 | The K"
    },
    {
        "title": "20220526 홍대 (hongdae busking) 유투버,틱톡커(임유진) 친한 지인들과 함께 버스킹 04 - (쥬쥬)Brave Girls - Rollin' (롤린)",
        "views": "조회수 546회",
        "upload_date": "2년 전",
        "channel_name": "dongsub jin"
    },
    {
        "title": "술먹방하기전 피파BJ들끼리 입수하는데 임유진에 이어 백크까지입수?!!",
        "views": "조회수 5.8만회",
        "upload_date": "1년 전",
        "channel_name": "마빡"
    },
    {
        "title": "[세무사 시험] 2024년 세무사 2차 시험 회계학 1부&세법학 1,2부 문제풀이",
        "views": "조회수 455회",
        "upload_date": "1일 전",
        "channel_name": "바른생각 회계사 세무사"
    },
    {
        "title": "🎶찬양의 부르심｜대구태현교회 임마누엘찬양대❤｜2024-09-08",
        "views": "조회수 62회",
        "upload_date": "3일 전",
        "channel_name": "대구태현교회TV"
    },
    {
        "title": "삼성·LG, 'AI-친환경'으로 유럽 진격 [말하는 기자들_산업_0910]",
        "views": "조회수 327회",
        "upload_date": "1일 전",
        "channel_name": "뉴스토마토"
    },
    {
        "title": "(길 잃은 2030 일자리) 20대 태반이 ‘백수’ [말하는 기자들_산업_0909]",
        "views": "조회수 145회",
        "upload_date": "1일 전",
        "channel_name": "뉴스토마토"
    },
    {
        "title": "[2023 일이관지(一以貫之) 공연실황] 10/19(목) 조선춤방Ⅰ (조갑녀, 박금슬 춤방) (Cho Kap-nyeo, Park Guem-sul Dance Room)",
        "views": "조회수 114회",
        "upload_date": "1일 전",
        "channel_name": "국립국악원[National Gugak Center]"
    },
    {
        "title": "깔끔하게 그린 온⛳️ 장민호 골프실력 극성수기👍 TV CHOSUN 220611 방송 | [골프왕3] 10회  | TV조선",
        "views": "조회수 7.9만회",
        "upload_date": "2년 전",
        "channel_name": "TVCHOSUN - TV조선"
    },
    {
        "title": "동창이 알게된 유튜브 | 100만원 소비 | 대전 1박2일, 고속노화 라이프 | 개망한 취준 week ⛏",
        "views": "조회수 4만회",
        "upload_date": "14시간 전",
        "channel_name": "도민이"
    },
    {
        "title": "연예인 행사비 최초 공개 | 레인보우18 (조현영, 고우리) EP.07",
        "views": "조회수 4.8만회",
        "upload_date": "21시간 전",
        "channel_name": "탁탁 TAKTAK"
    },
    {
        "title": "240827 창현고 채플",
        "views": "조회수 129회",
        "upload_date": "3일 전",
        "channel_name": "창현고 호산나"
    },
    {
        "title": "총수들, 추석 연휴에도 '경영 구상' [말하는 기자들_산업_0911]",
        "views": "조회수 없음",
        "upload_date": "6분 전",
        "channel_name": "뉴스토마토"
    },
    {
        "title": "[상트콤] 이상호 놀래키기 3초전 레전드 ㅋㅋㅋㅋㅋㅋ",
        "views": "조회수 25만회",
        "upload_date": "1일 전",
        "channel_name": "이상호"
    },
    {
        "title": "성령이 오셨네 (JCU 토요예배 찬양)",
        "views": "조회수 149회",
        "upload_date": "1일 전",
        "channel_name": "JCU 예수중심대학부 (예수중심교회 대학부)"
    },
    {
        "title": "나도 연애 좀 하자",
        "views": "조회수 5.9만회",
        "upload_date": "19시간 전",
        "channel_name": "김지오"
    },
    {
        "title": "윤석열 고집불통, 의정대화 교착-추석 '응급실 대란' 불 보듯-역대급 세수 결손에도 유산취득세 강행-'해리스냐 트럼프냐'…미국 대선 TV 토론 분수령 #뉴스리듬(0911_수)",
        "views": "조회수 447회",
        "upload_date": "스트리밍 시간: 1시간 전",
        "channel_name": "뉴스토마토"
    },
    {
        "title": "롤에서 가장 예쁜챔피언 ㅇㅈ?",
        "views": "조회수 2.3만회",
        "upload_date": "2일 전",
        "channel_name": "즐겜유저 호시노마이"
    },
    {
        "title": "프리웨이트 좋아하는 동탄 왕팔 선붸님.. feat.설기관",
        "views": "조회수 2.4만회",
        "upload_date": "1일 전",
        "channel_name": "킹유진"
    },
    {
        "title": "감스트 휴방을 마치고 복귀 방송 오프닝 토크 [24.9.4]",
        "views": "조회수 3.1만회",
        "upload_date": "6일 전",
        "channel_name": "겜스트GAMEST"
    },
    {
        "title": "나은아 이럴거면 나한테 고민상담 왜한거냐",
        "views": "조회수 3.7천회",
        "upload_date": "2시간 전",
        "channel_name": "진꼰대"
    },
    {
        "title": "[운빨존많겜] 오랜만에 하드&지옥모드 버스하러 왔습니다.",
        "views": "조회수 1만회",
        "upload_date": "스트리밍 시간: 12시간 전",
        "channel_name": "세웅"
    },
    {
        "title": "빅사이즈 테무깡.. 희망편😌 30만원어치인데 33개가 옴,, 갓성비 찾는다면 들어오세요.. +코디 조합 추천!✨",
        "views": "조회수 1.7만회",
        "upload_date": "1일 전",
        "channel_name": "모염 moyeom"
    },
    {
        "title": "벤츠 E클래스에서 쏘렌토로 갈아탄 이유! 오너 카터뷰",
        "views": "조회수 4만회",
        "upload_date": "2일 전",
        "channel_name": "이아나TV"
    },
    {
        "title": "미션금만 걸리면 귀신같이 해내는 나",
        "views": "조회수 1.5만회",
        "upload_date": "1일 전",
        "channel_name": "강소연 YouTube"
    },
    {
        "title": "A조 뽑아달라는 JD 조용하게 만드는 우승자 김민철의 협박ㅋㅋㅋㅋ(SSL1 조지명식 1부)",
        "views": "조회수 1.4만회",
        "upload_date": "1일 전",
        "channel_name": "변현제TV"
    },
    {
        "title": "[JOY #Shorts] 윤태영 6언더 실력 보여준 Par3 원온 티샷 #골프왕 #TV조선조이 #TVCHOSUNJOY (TV CHOSUN 220709 방송)",
        "views": "조회수 1.1만회",
        "upload_date": "2년 전",
        "channel_name": "TVCHOSUN JOY"
    },
    {
        "title": "맨션에서 주최한 파티에 다녀왔어용~풀버전은 릴스에⭐️",
        "views": "조회수 1.2만회",
        "upload_date": "2일 전",
        "channel_name": "himemong"
    },
    {
        "title": "1카 기준 1등은?",
        "views": "조회수 13만회",
        "upload_date": "3일 전",
        "channel_name": "텐스튜디오"
    },
    {
        "title": "거- 주인장 먹는거로 장난치지마쇼ㅡㅡ",
        "views": "조회수 7.5천회",
        "upload_date": "1일 전",
        "channel_name": "이녕"
    },
    {
        "title": "인생 최초 찐텐 욕설.. 타임라인",
        "views": "조회수 5.5만회",
        "upload_date": "2일 전",
        "channel_name": "이아린 Ahrin"
    },
    {
        "title": "비타민TV/이진숙 방통위원장#이진숙",
        "views": "조회수 385회",
        "upload_date": "5시간 전",
        "channel_name": "비타민TV"
    },
    {
        "title": "비오는 남산/모델MC가수 임유진",
        "views": "조회수 16회",
        "upload_date": "3일 전",
        "channel_name": "배홍(모델mc가수)TV"
    },
    {
        "title": "240910 창현고 채플",
        "views": "조회수 없음",
        "upload_date": "16시간 전",
        "channel_name": "창현고 호산나"
    },
    {
        "title": "역대급 성형 전후 TOP3 #Shorts",
        "views": "조회수 42만회",
        "upload_date": "3년 전",
        "channel_name": "뷰티푸르"
    },
    {
        "title": "한유진&운학이의 초등학교 교가 배틀  | 대친소 EP.861 | Mnet Plus | MCD",
        "views": "조회수 5천회",
        "upload_date": "2일 전",
        "channel_name": "Mnet Plus"
    },
    {
        "title": "[청주대 댄스동아리 ABLE] TWS - hey! hey! | KPOP IN PUBLIC 커버댄스 dance cover",
        "views": "조회수 308회",
        "upload_date": "3일 전",
        "channel_name": "[ABLE]청주대학교 댄스동아리 에이블"
    },
    {
        "title": "5000원으로 즐기는 제주도여행",
        "views": "조회수 6.5천회",
        "upload_date": "2일 전",
        "channel_name": "강소연 YouTube"
    },
    {
        "title": "나도 조만간 연애중❤️ 올린다.",
        "views": "조회수 3.5천회",
        "upload_date": "1일 전",
        "channel_name": "쭐리아"
    },
    {
        "title": "청주1부) 친구 결혼식 축가를!? 거노에서 부르는 패왕색 패기남",
        "views": "조회수 7.3천회",
        "upload_date": "2일 전",
        "channel_name": "창현거리노래방 Korea amazing street performers"
    },
    {
        "title": "일상브이로그 | 내가 임신했다고?!?? (임테기/임밍아웃/임신 초기 일상)",
        "views": "조회수 893회",
        "upload_date": "1일 전",
        "channel_name": "지투Jitwo"
    },
    {
        "title": "솔로냐 유부냐 [#고장난형제들]",
        "views": "조회수 567회",
        "upload_date": "2일 전",
        "channel_name": "Maeil"
    },
    {
        "title": "알파남이 길을 물어볼 때 #shorts",
        "views": "조회수 3.4천회",
        "upload_date": "20시간 전",
        "channel_name": "이게 최우선"
    },
    {
        "title": "멸망전 최종전 임아니 VS 김민교팀 구경하기 [24.09.09]",
        "views": "조회수 677회",
        "upload_date": "1일 전",
        "channel_name": "안녕수야 다시보기"
    },
    {
        "title": "멸망전에서 하이퍼 캐리 원딜을 뽑으면 생기는 일",
        "views": "조회수 3.2천회",
        "upload_date": "2일 전",
        "channel_name": "이브"
    },
    {
        "title": "장유진(충남도청) vs 김잔디(삼성에스원) | 준결승 여자일반부 -67kg급 | 제33회 국방부장관기 전국단체대항태권도대회",
        "views": "조회수 96회",
        "upload_date": "3시간 전",
        "channel_name": "대한태권도협회"
    },
    {
        "title": "인선을 짝사랑하는 태환에게 날리는 유진의 날카로운 한마디⚡ TV CHOSUN 240908 방송 | [DNA러버] 8회 | TV조선",
        "views": "조회수 408회",
        "upload_date": "2일 전",
        "channel_name": "TVCHOSUN - TV조선"
    },
    {
        "title": "그대가 떠나면 어쩌나! [우리진영 #우진영 / #공감&코드] #비금오빠",
        "views": "조회수 127회",
        "upload_date": "3시간 전",
        "channel_name": "비금오빠"
    },
    {
        "title": "그만좀 괴롭혀ㅠㅠㅠ 괴식룰렛 ... 시작..",
        "views": "조회수 4.1천회",
        "upload_date": "스트리밍 시간: 2일 전",
        "channel_name": "이녕"
    },
    {
        "title": "[JOY BOX] 원래는 비슷했어요^^ 이완이 말하는 매형 비(Rain)의 골프 실력은?! #골프왕 #TV조선조이 (TV CHOSUN 220618 방송)",
        "views": "조회수 4.2만회",
        "upload_date": "2년 전",
        "channel_name": "TVCHOSUN JOY"
    },
    {
        "title": "[D-1] 몸만 큰 아이 (Feat. 이지(Eazy)) - 015B 내일(11일) 정오 공개됩니다.",
        "views": "조회수 223회",
        "upload_date": "23시간 전",
        "channel_name": "015B"
    },
    {
        "title": "유튜브 쉽지않다.. 일단 말부터 다시 배우자 ㅋㅋㅋ",
        "views": "조회수 31회",
        "upload_date": "18시간 전",
        "channel_name": "임작가 반짝반짝 JEJU "
    },
    {
        "title": "[REVIEW / 4K] 이젠 철들어버린 남자처럼 변해버린 차. G82 M4 컴페티션 리뷰 l OVERIDE",
        "views": "조회수 197회",
        "upload_date": "19시간 전",
        "channel_name": "OVERIDE"
    },
    {
        "title": "#태태씨생존신고1😎#오랜만에필드샷🏌‍♀️#리액션부자😻#우리회원님🫶#BOSS테니스웨어라운딩룩에도세상예뻐🤩#영산스포츠에서구매가능해여😊",
        "views": "조회수 550회",
        "upload_date": "2일 전",
        "channel_name": "뺀질한태태씨🙃"
    },
    {
        "title": "[제베원] 태건브이 사진 썰 #김태래 #박건욱",
        "views": "조회수 3.5천회",
        "upload_date": "1일 전",
        "channel_name": "탤랑"
    }
]